src/alu.v
module alu (
    input wire [31:0] a, b,
    input wire [3:0] alu_control,
    output reg [31:0] result,
    output wire zero
);

    assign zero = (result == 0);

    always @(*) begin
        case (alu_control)
            4'b0000: result = a & b;                     // AND
            4'b0001: result = a | b;                     // OR
            4'b0010: result = a + b;                     // ADD
            4'b0110: result = a - b;                     // SUB
            4'b0011: result = a ^ b;                     // XOR
            4'b0100: result = a << b[4:0];               // SLL
            4'b0101: result = a >> b[4:0];               // SRL
            4'b1101: result = $signed(a) >>> b[4:0];     // SRA
            4'b0111: result = ($signed(a) < $signed(b)) ? 1 : 0; // SLT
            4'b1000: result = (a < b) ? 1 : 0;           // SLTU
            default: result = 0;
        endcase
    end
endmodule

src/imm_gen.v
module imm_gen (
    input wire [31:0] instr,
    output reg [31:0] imm_out
);
    always @(*) begin
        case (instr[6:0])
            7'b0010011, // I-type ALU
            7'b0000011, // Loads
            7'b1100111: // JALR
                imm_out = {{20{instr[31]}}, instr[31:20]};
            7'b0100011: // S-type stores
                imm_out = {{20{instr[31]}}, instr[31:25], instr[11:7]};
            7'b1100011: // B-type branches
                imm_out = {{19{instr[31]}}, instr[31], instr[7], instr[30:25], instr[11:8], 1'b0};
            7'b0110111, // LUI
            7'b0010111: // AUIPC
                imm_out = {instr[31:12], 12'b0};
            7'b1101111: // J-type JAL
                imm_out = {{11{instr[31]}}, instr[31], instr[19:12], instr[20], instr[30:21], 1'b0};
            default:
                imm_out = 32'b0;
        endcase
    end
endmodule

accel_cpu/src/alu_control.v
module alu_control (
    input wire [1:0] ALUOp,
    input wire [2:0] funct3,
    input wire [6:0] funct7,
    output reg [3:0] alu_control
);
    always @(*) begin
        case (ALUOp)
            2'b00: alu_control = 4'b0010;  // lw, sw → ADD
            2'b01: alu_control = 4'b0110;  // branch → SUB
            2'b10: begin  // R-type
                case ({funct7, funct3})
                    10'b0000000_000: alu_control = 4'b0010; // ADD
                    10'b0100000_000: alu_control = 4'b0110; // SUB
                    10'b0000000_001: alu_control = 4'b0100; // SLL
                    10'b0000000_010: alu_control = 4'b0111; // SLT
                    10'b0000000_011: alu_control = 4'b1000; // SLTU
                    10'b0000000_100: alu_control = 4'b0011; // XOR
                    10'b0000000_101: alu_control = 4'b0101; // SRL
                    10'b0100000_101: alu_control = 4'b1101; // SRA
                    10'b0000000_110: alu_control = 4'b0001; // OR
                    10'b0000000_111: alu_control = 4'b0000; // AND
                    10'b0000001_000: alu_control = 4'b1001; // MUL
                    default: alu_control = 4'b1111; // INVALID
                endcase
            end
            2'b11: begin  // I-type ALU ops
                case (funct3)
                    3'b000: alu_control = 4'b0010; // ADDI
                    3'b010: alu_control = 4'b0111; // SLTI
                    3'b011: alu_control = 4'b1000; // SLTIU
                    3'b100: alu_control = 4'b0011; // XORI
                    3'b110: alu_control = 4'b0001; // ORI
                    3'b111: alu_control = 4'b0000; // ANDI
                    3'b001: alu_control = 4'b0100; // SLLI
                    3'b101: alu_control = (funct7[5]) ? 4'b1101 : 4'b0101; // SRAI / SRLI
                    default: alu_control = 4'b1111;
                endcase
            end
            default: alu_control = 4'b1111;
        endcase
    end
endmodule

src/regfile.v
module regfile (
    input wire clk,
    input wire reset,
    input wire we,                         // Write enable
    input wire [4:0] rs1, rs2, rd,         // Register addresses
    input wire [31:0] wd,                  // Write data
    output wire [31:0] rd1, rd2            // Read data outputs
);
    reg [31:0] regs [0:31];

    // Read (asynchronous)
    assign rd1 = (rs1 == 0) ? 0 : regs[rs1];
    assign rd2 = (rs2 == 0) ? 0 : regs[rs2];

    // Write with synchronous reset
    integer i;
    always @(posedge clk) begin
        if (reset) begin
            for (i = 0; i < 32; i = i + 1)
                regs[i] <= 0;
        end else if (we && (rd != 0)) begin
            regs[rd] <= wd;
        end
    end
endmodule

base_cpu/src/execute.v
module execute (
    input wire clk,
    input wire reset,
    input wire we,                     // Write enable for register file
    input wire [1:0] alu_op,          // ALUOp from control unit
    input wire [4:0] rs1, rs2, rd,    // Register addresses
    input wire [31:0] instr,          // Full instruction for immediate generation
    input wire alu_src,               // Select between register or immediate
    input wire [2:0] funct3,
    input wire [6:0] funct7,
    input wire [31:0] wb_data,        // Data to write back to register file
    output wire [31:0] alu_result,
    output wire zero,
    output wire [31:0] rd1, rd2
);

    wire [31:0] op2;
    wire [3:0] alu_control;
    wire [31:0] imm;

    // Register file
    regfile rf (
        .clk(clk),
        .reset(reset),
        .we(we),
        .rs1(rs1),
        .rs2(rs2),
        .rd(rd),
        .wd(wb_data),
        .rd1(rd1),
        .rd2(rd2)
    );

    // ALU control
    alu_control alu_ctl (
        .ALUOp(alu_op),
        .funct3(funct3),
        .funct7(funct7),
        .alu_control(alu_control)
    );

    // Immediate generator
    imm_gen imm_generator (
        .instr(instr),
        .imm_out(imm)
    );

    // ALU second operand selection
    assign op2 = (alu_src) ? imm : rd2;

    // ALU
    alu alu_core (
        .a(rd1),
        .b(op2),
        .alu_control(alu_control),
        .result(alu_result),
        .zero(zero)
    );

endmodule

base_cpu/src/data_mem.v
module data_mem(
    input wire clk,
    input wire mem_read,
    input wire mem_write,
    input wire [31:0] addr,
    input wire [31:0] write_data,
    output wire [31:0] read_data
);
    reg [31:0] mem [0:255];

    initial begin
        // Optionally pre-load memory from file
    end

    always @(posedge clk) begin
        if (mem_write) begin
            mem[addr[9:2]] <= write_data;
        end
    end

    assign read_data = mem_read ? mem[addr[9:2]] : 32'b0;
endmodule

base_cpu/src/control_unit.v
module control_unit(
    input  wire [6:0] opcode,
    input  wire [2:0] funct3,
    input  wire [6:0] funct7,
    output reg  [1:0] ALUOp,
    output reg  RegWrite,
    output reg  MemRead,
    output reg  MemWrite,
    output reg  Branch,
    output reg  Jump,
    output reg  ALUSrc
);

    always @(*) begin
        // Default values
        ALUOp    = 2'b00;
        RegWrite = 0;
        MemRead  = 0;
        MemWrite = 0;
        Branch   = 0;
        Jump     = 0;
        ALUSrc   = 0;

        case (opcode)
            7'b0110011: begin // R-type
                RegWrite = 1;
                ALUOp    = 2'b10;
                ALUSrc   = 0;
            end
            7'b0010011: begin // I-type ALU
                RegWrite = 1;
                ALUOp    = 2'b11;
                ALUSrc   = 1;
            end
            7'b0000011: begin // Load
                RegWrite = 1;
                MemRead  = 1;
                ALUOp    = 2'b00;
                ALUSrc   = 1;
            end
            7'b0100011: begin // Store
                MemWrite = 1;
                ALUOp    = 2'b00;
                ALUSrc   = 1;
            end
            7'b1100011: begin // Branch
                Branch   = 1;
                ALUOp    = 2'b01;
                ALUSrc   = 0;
            end
            7'b1101111: begin // JAL
                Jump     = 1;
                RegWrite = 1;
            end
            7'b1100111: begin // JALR
                Jump     = 1;
                RegWrite = 1;
                ALUSrc   = 1;
                ALUOp    = 2'b00;
            end
            default: begin
            end
        endcase
    end
endmodule

src/instr_mem.v
module instr_mem #(
    parameter INIT_FILE = "program.mem"
) (
    input wire [31:0] addr,
    output wire [31:0] instr
);
    reg [31:0] mem [0:255];  // 1KB instruction memory (256 words)

    initial begin
        $readmemh(INIT_FILE, mem);  // Load instructions from hex file
    end

    assign instr = mem[addr[9:2]];  // Word-aligned address (ignore bottom 2 bits)
endmodule

accel_cpu/src/pc.v
module pc(
    input wire clk,
    input wire reset,
    input wire [31:0] next_pc,
    output reg [31:0] pc_out
);
    always @(posedge clk or posedge reset) begin
        if (reset)
            pc_out <= 32'h00000000;
        else
            pc_out <= next_pc;
    end
endmodule

src/cpu_fetch.v
module cpu_fetch #(
    parameter MEMFILE = "program.mem"
) (
    input  wire        clk,
    input  wire        reset,

    // Control signals / targets
    input  wire        jal,            // jal instruction
    input  wire        jalr,           // jalr instruction
    input  wire        branch,         // conditional branch instruction
    input  wire        branch_taken,   // result of branch comparison from ALU
    input  wire [31:0] branch_target,  // PC-relative target for jal/branch
    input  wire [31:0] jalr_target,    // Target address for jalr

    output wire [31:0] instr,
    output wire [31:0] pc_out
);
    wire [31:0] next_pc;

    // Program Counter instance
    pc pc_inst (
        .clk(clk),
        .reset(reset),
        .next_pc(next_pc),
        .pc_out(pc_out)
    );

    // Instruction Memory instance
    instr_mem #(.INIT_FILE(MEMFILE)) imem (
        .addr(pc_out),
        .instr(instr)
    );

    // Next PC generation with branch/jump handling
    wire [31:0] pc_plus4 = pc_out + 4;

    assign next_pc = jal  ? branch_target :
                     jalr ? jalr_target  :
                     (branch && branch_taken) ? branch_target :
                     pc_plus4;

endmodule

base_cpu/src/cpu.v
module cpu #(
    parameter MEMFILE = "program.mem"
) (
    input wire clk,
    input wire reset,
    output reg [31:0] cycle_count
);
    wire [31:0] instr;
    wire [31:0] pc_out;

    // Performance counters
    reg [31:0] instr_count;
    reg [31:0] mem_read_count;
    reg [31:0] mem_write_count;
    reg [31:0] rf_read_count;
    reg [31:0] rf_write_count;

    // Signals for fetch stage
    wire jal, jalr;
    wire branch_taken;
    wire [31:0] branch_target, jalr_target;

    cpu_fetch #(.MEMFILE(MEMFILE)) fetch_unit(
        .clk(clk),
        .reset(reset),
        .jal(jal),
        .jalr(jalr),
        .branch(Branch),
        .branch_taken(branch_taken),
        .branch_target(branch_target),
        .jalr_target(jalr_target),
        .instr(instr),
        .pc_out(pc_out)
    );

    // Decode fields
    wire [6:0] opcode = instr[6:0];
    wire [2:0] funct3 = instr[14:12];
    wire [6:0] funct7 = instr[31:25];

    // Halt detection (using the EBREAK instruction)
    wire halt = (instr == 32'h0010_0073);
    wire [4:0] rd  = instr[11:7];
    wire [4:0] rs1 = instr[19:15];
    wire [4:0] rs2 = instr[24:20];

    // Immediate generator
    wire [31:0] imm;
    imm_gen imm_unit(
        .instr(instr),
        .imm_out(imm)
    );

    // Control signals
    wire [1:0] ALUOp;
    wire RegWrite, MemRead, MemWrite, Branch, Jump, ALUSrc;

    control_unit cu(
        .opcode(opcode),
        .funct3(funct3),
        .funct7(funct7),
        .ALUOp(ALUOp),
        .RegWrite(RegWrite),
        .MemRead(MemRead),
        .MemWrite(MemWrite),
        .Branch(Branch),
        .Jump(Jump),
        .ALUSrc(ALUSrc)
    );

    // Register and ALU outputs
    wire [31:0] alu_result;
    wire zero;
    wire [31:0] rd1, rd2;
    wire [31:0] write_back_data;

    // Data memory
    wire [31:0] mem_data;
    data_mem dmem(
        .clk(clk),
        .mem_read(MemRead),
        .mem_write(MemWrite),
        .addr(alu_result),
        .write_data(rd2),
        .read_data(mem_data)
    );


    execute exec_unit(
        .clk(clk),
        .reset(reset),
        .we(RegWrite),
        .alu_op(ALUOp),
        .rs1(rs1),
        .rs2(rs2),
        .rd(rd),
        .instr(instr),
        .alu_src(ALUSrc),
        .funct3(funct3),
        .funct7(funct7),
        .wb_data(write_back_data),
        .alu_result(alu_result),
        .zero(zero),
        .rd1(rd1),
        .rd2(rd2)
    );

    // PC increment
    wire [31:0] pc_plus4 = pc_out + 4;

    // Branch and jump target calculations
    assign branch_target = pc_out + imm;
    assign jalr_target   = (rd1 + imm) & 32'hffff_fffe;

    // Branch comparison helpers
    wire eq      = (rd1 == rd2);
    wire slt     = ($signed(rd1) < $signed(rd2));
    wire sltu    = (rd1 < rd2);

    // Branch decision based on funct3
    reg branch_cond;
    always @(*) begin
        case (funct3)
            3'b000: branch_cond = eq;          // BEQ
            3'b001: branch_cond = !eq;         // BNE
            3'b100: branch_cond = slt;         // BLT
            3'b101: branch_cond = !slt;        // BGE
            3'b110: branch_cond = sltu;        // BLTU
            3'b111: branch_cond = !sltu;       // BGEU
            default: branch_cond = 1'b0;
        endcase
    end

    assign branch_taken = Branch && branch_cond;

    // Distinguish between JAL and JALR
    assign jal  = Jump && (opcode == 7'b1101111);
    assign jalr = Jump && (opcode == 7'b1100111);

    // Writeback mux: priority Jump -> Load -> ALU
    assign write_back_data = jal | jalr ? pc_plus4 :
                              MemRead    ? mem_data  :
                              alu_result;

    // Cycle counter and other performance metrics
    always @(posedge clk) begin
        if (reset) begin
            cycle_count     <= 0;
            instr_count     <= 0;
            mem_read_count  <= 0;
            mem_write_count <= 0;
            rf_read_count   <= 0;
            rf_write_count  <= 0;
        end else if (!halt) begin
            cycle_count <= cycle_count + 1;
            instr_count <= instr_count + 1;

            // Memory access counters
            if (MemRead)
                mem_read_count <= mem_read_count + 1;
            if (MemWrite)
                mem_write_count <= mem_write_count + 1;

            // Register file read counters
            if ((opcode != 7'b1101111) && (rs1 != 0))
                rf_read_count <= rf_read_count + 1;
            if ((opcode == 7'b0110011 || opcode == 7'b0100011 || opcode == 7'b1100011) && (rs2 != 0))
                rf_read_count <= rf_read_count + 1;

            // Register file write counter
            if (RegWrite && rd != 0)
                rf_write_count <= rf_write_count + 1;
        end
    end

    // TODO: Power estimation hooks can be added for FPGA implementation
endmodule

accel_cpu/testbench/cpu_matmul_tb.v
`timescale 1ns / 1ps

module cpu_matmul_tb;
    reg clk = 0;
    reg reset;
    wire [31:0] cycle_count;
    wire [31:0] instr_count      = uut.instr_count;
    wire [31:0] mem_read_count   = uut.mem_read_count;
    wire [31:0] mem_write_count  = uut.mem_write_count;
    wire [31:0] rf_read_count    = uut.rf_read_count;
    wire [31:0] rf_write_count   = uut.rf_write_count;

    cpu #(.MEMFILE("test_mem/matmul.mem")) uut (
        .clk(clk),
        .reset(reset),
        .cycle_count(cycle_count)
    );

    always #5 clk = ~clk;

    initial begin
        $dumpfile("sim/cpu_matmul_tb.vcd");
        $dumpvars(0, cpu_matmul_tb);
        $display("=== 2x2 Matrix Multiplication Benchmark ===");

        reset = 1;
        @(posedge clk); @(posedge clk); reset = 0;

        repeat(30) @(posedge clk); #1;
        $display("C00=%0d C01=%0d C10=%0d C11=%0d",
                 uut.exec_unit.rf.regs[11],
                 uut.exec_unit.rf.regs[12],
                 uut.exec_unit.rf.regs[13],
                 uut.exec_unit.rf.regs[14]);
        $display("Cycles       : %0d", cycle_count);
        $display("Instructions : %0d", instr_count);
        $display("Mem reads    : %0d", mem_read_count);
        $display("Mem writes   : %0d", mem_write_count);
        $display("RF reads     : %0d", rf_read_count);
        $display("RF writes    : %0d", rf_write_count);
        $finish;
    end
endmodule

base_cpu/sim/cpu_matmul_tb.vcd
$date
	Tue Jul  1 01:54:32 2025
$end
$version
	Icarus Verilog
$end
$timescale
	1ps
$end
$scope module cpu_matmul_tb $end
$var wire 32 ! instr_count [31:0] $end
$var wire 32 " mem_read_count [31:0] $end
$var wire 32 # mem_write_count [31:0] $end
$var wire 32 $ rf_read_count [31:0] $end
$var wire 32 % rf_write_count [31:0] $end
$var wire 32 & cycle_count [31:0] $end
$var reg 1 ' clk $end
$var reg 1 ( reset $end
$scope module uut $end
$var wire 1 ) branch_taken $end
$var wire 1 ' clk $end
$var wire 1 * jal $end
$var wire 1 + jalr $end
$var wire 32 , jalr_target [31:0] $end
$var wire 1 ( reset $end
$var wire 1 - zero $end
$var wire 32 . write_back_data [31:0] $end
$var wire 1 / sltu $end
$var wire 1 0 slt $end
$var wire 5 1 rs2 [4:0] $end
$var wire 5 2 rs1 [4:0] $end
$var wire 32 3 rd2 [31:0] $end
$var wire 32 4 rd1 [31:0] $end
$var wire 5 5 rd [4:0] $end
$var wire 32 6 pc_plus4 [31:0] $end
$var wire 32 7 pc_out [31:0] $end
$var wire 7 8 opcode [6:0] $end
$var wire 32 9 mem_data [31:0] $end
$var wire 32 : instr [31:0] $end
$var wire 32 ; imm [31:0] $end
$var wire 1 < halt $end
$var wire 7 = funct7 [6:0] $end
$var wire 3 > funct3 [2:0] $end
$var wire 1 ? eq $end
$var wire 32 @ branch_target [31:0] $end
$var wire 32 A alu_result [31:0] $end
$var wire 1 B RegWrite $end
$var wire 1 C MemWrite $end
$var wire 1 D MemRead $end
$var wire 1 E Jump $end
$var wire 1 F Branch $end
$var wire 1 G ALUSrc $end
$var wire 2 H ALUOp [1:0] $end
$var parameter 152 I MEMFILE $end
$var reg 1 J branch_cond $end
$var reg 32 K cycle_count [31:0] $end
$var reg 32 L instr_count [31:0] $end
$var reg 32 M mem_read_count [31:0] $end
$var reg 32 N mem_write_count [31:0] $end
$var reg 32 O rf_read_count [31:0] $end
$var reg 32 P rf_write_count [31:0] $end
$scope module cu $end
$var wire 3 Q funct3 [2:0] $end
$var wire 7 R funct7 [6:0] $end
$var wire 7 S opcode [6:0] $end
$var reg 2 T ALUOp [1:0] $end
$var reg 1 G ALUSrc $end
$var reg 1 F Branch $end
$var reg 1 E Jump $end
$var reg 1 D MemRead $end
$var reg 1 C MemWrite $end
$var reg 1 B RegWrite $end
$upscope $end
$scope module dmem $end
$var wire 1 ' clk $end
$var wire 1 D mem_read $end
$var wire 1 C mem_write $end
$var wire 32 U write_data [31:0] $end
$var wire 32 V read_data [31:0] $end
$var wire 32 W addr [31:0] $end
$upscope $end
$scope module exec_unit $end
$var wire 2 X alu_op [1:0] $end
$var wire 1 G alu_src $end
$var wire 1 ' clk $end
$var wire 3 Y funct3 [2:0] $end
$var wire 7 Z funct7 [6:0] $end
$var wire 5 [ rd [4:0] $end
$var wire 1 ( reset $end
$var wire 5 \ rs1 [4:0] $end
$var wire 5 ] rs2 [4:0] $end
$var wire 32 ^ wb_data [31:0] $end
$var wire 1 B we $end
$var wire 1 - zero $end
$var wire 32 _ rd2 [31:0] $end
$var wire 32 ` rd1 [31:0] $end
$var wire 32 a op2 [31:0] $end
$var wire 32 b instr [31:0] $end
$var wire 32 c imm [31:0] $end
$var wire 32 d alu_result [31:0] $end
$var wire 4 e alu_control [3:0] $end
$scope module alu_core $end
$var wire 32 f b [31:0] $end
$var wire 1 - zero $end
$var wire 4 g alu_control [3:0] $end
$var wire 32 h a [31:0] $end
$var reg 32 i result [31:0] $end
$upscope $end
$scope module alu_ctl $end
$var wire 2 j ALUOp [1:0] $end
$var wire 3 k funct3 [2:0] $end
$var wire 7 l funct7 [6:0] $end
$var reg 4 m alu_control [3:0] $end
$upscope $end
$scope module imm_generator $end
$var wire 32 n instr [31:0] $end
$var reg 32 o imm_out [31:0] $end
$upscope $end
$scope module rf $end
$var wire 1 ' clk $end
$var wire 5 p rd [4:0] $end
$var wire 1 ( reset $end
$var wire 5 q rs1 [4:0] $end
$var wire 5 r rs2 [4:0] $end
$var wire 32 s wd [31:0] $end
$var wire 1 B we $end
$var wire 32 t rd2 [31:0] $end
$var wire 32 u rd1 [31:0] $end
$var integer 32 v i [31:0] $end
$upscope $end
$upscope $end
$scope module fetch_unit $end
$var wire 1 F branch $end
$var wire 1 ) branch_taken $end
$var wire 32 w branch_target [31:0] $end
$var wire 1 ' clk $end
$var wire 1 * jal $end
$var wire 1 + jalr $end
$var wire 32 x jalr_target [31:0] $end
$var wire 1 ( reset $end
$var wire 32 y pc_plus4 [31:0] $end
$var wire 32 z pc_out [31:0] $end
$var wire 32 { next_pc [31:0] $end
$var wire 32 | instr [31:0] $end
$var parameter 152 } MEMFILE $end
$scope module imem $end
$var wire 32 ~ instr [31:0] $end
$var wire 32 !" addr [31:0] $end
$var parameter 152 "" INIT_FILE $end
$upscope $end
$scope module pc_inst $end
$var wire 1 ' clk $end
$var wire 32 #" next_pc [31:0] $end
$var wire 1 ( reset $end
$var reg 32 $" pc_out [31:0] $end
$upscope $end
$upscope $end
$scope module imm_unit $end
$var wire 32 %" instr [31:0] $end
$var reg 32 &" imm_out [31:0] $end
$upscope $end
$upscope $end
$upscope $end
$enddefinitions $end
$comment Show the parameter values. $end
$dumpall
b1110100011001010111001101110100010111110110110101100101011011010010111101101101011000010111010001101101011101010110110000101110011011010110010101101101 ""
b1110100011001010111001101110100010111110110110101100101011011010010111101101101011000010111010001101101011101010110110000101110011011010110010101101101 }
b1110100011001010111001101110100010111110110110101100101011011010010111101101101011000010111010001101101011101010110110000101110011011010110010101101101 I
$end
#0
$dumpvars
b1 &"
b100000000000010010011 %"
b0 $"
b100 #"
b0 !"
b100000000000010010011 ~
b100000000000010010011 |
b100 {
b0 z
b100 y
b0 x
b1 w
bx v
b0 u
bx t
b1 s
b1 r
b0 q
b1 p
b1 o
b100000000000010010011 n
b10 m
b0 l
b0 k
b11 j
b1 i
b0 h
b10 g
b1 f
b10 e
b1 d
b1 c
b100000000000010010011 b
b1 a
b0 `
bx _
b1 ^
b1 ]
b0 \
b1 [
b0 Z
b0 Y
b11 X
b1 W
b0 V
bx U
b11 T
b10011 S
b0 R
b0 Q
bx P
bx O
bx N
bx M
bx L
bx K
xJ
b11 H
1G
0F
0E
0D
0C
1B
b1 A
b1 @
x?
b0 >
b0 =
0<
b1 ;
b100000000000010010011 :
b0 9
b10011 8
b0 7
b100 6
b1 5
b0 4
bx 3
b0 2
b1 1
x0
x/
b1 .
0-
b0 ,
0+
0*
0)
1(
0'
bx &
bx %
bx $
bx #
bx "
bx !
$end
#5000
1J
0/
00
1?
b0 3
b0 U
b0 _
b0 t
b0 %
b0 P
b0 $
b0 O
b0 #
b0 N
b0 "
b0 M
b0 !
b0 L
b0 &
b0 K
b100000 v
1'
#10000
0'
#15000
0(
b100000 v
1'
#20000
0'
#25000
b10 .
b10 ^
b10 s
b10 A
b10 W
b10 d
b10 i
b10 ,
b10 x
b10 a
b10 f
b1000 {
b1000 #"
1J
b10 1
b10 ]
b10 r
b10 5
b10 [
b10 p
b10 ;
b10 &"
b10 c
b10 o
0/
00
1?
b0 3
b0 U
b0 _
b0 t
b1000000000000100010011 :
b1000000000000100010011 b
b1000000000000100010011 n
b1000000000000100010011 |
b1000000000000100010011 ~
b1000000000000100010011 %"
b1 %
b1 P
b1 !
b1 L
b1 &
b1 K
b1000 y
b110 @
b110 w
b1000 6
b100 7
b100 z
b100 !"
b100 $"
1'
#30000
0'
#35000
b11 .
b11 ^
b11 s
b11 A
b11 W
b11 d
b11 i
b11 a
b11 f
b1100 {
b1100 #"
1J
b11 1
b11 ]
b11 r
b11 5
b11 [
b11 p
b11 c
b11 o
b11 ;
b11 &"
0/
00
1?
b0 3
b0 U
b0 _
b0 t
b1100000000000110010011 :
b1100000000000110010011 b
b1100000000000110010011 n
b1100000000000110010011 |
b1100000000000110010011 ~
b1100000000000110010011 %"
b10 %
b10 P
b10 !
b10 L
b10 &
b10 K
b1100 y
b1011 @
b1011 w
b1100 6
b1000 7
b1000 z
b1000 !"
b1000 $"
1'
#40000
0'
#45000
b100 .
b100 ^
b100 s
b100 A
b100 W
b100 d
b100 i
b100 ,
b100 x
b100 a
b100 f
b10000 {
b10000 #"
1J
b100 1
b100 ]
b100 r
b100 5
b100 [
b100 p
b100 ;
b100 &"
b100 c
b100 o
0/
00
1?
b0 3
b0 U
b0 _
b0 t
b10000000000001000010011 :
b10000000000001000010011 b
b10000000000001000010011 n
b10000000000001000010011 |
b10000000000001000010011 ~
b10000000000001000010011 %"
b11 %
b11 P
b11 !
b11 L
b11 &
b11 K
b10000 y
b10000 @
b10000 w
b10000 6
b1100 7
b1100 z
b1100 !"
b1100 $"
1'
#50000
0'
#55000
b101 .
b101 ^
b101 s
b101 A
b101 W
b101 d
b101 i
b101 a
b101 f
b10100 {
b10100 #"
1J
b101 1
b101 ]
b101 r
b101 5
b101 [
b101 p
b101 c
b101 o
b101 ;
b101 &"
0/
00
1?
b0 3
b0 U
b0 _
b0 t
b10100000000001010010011 :
b10100000000001010010011 b
b10100000000001010010011 n
b10100000000001010010011 |
b10100000000001010010011 ~
b10100000000001010010011 %"
b100 %
b100 P
b100 !
b100 L
b100 &
b100 K
b10100 y
b10101 @
b10101 w
b10100 6
b10000 7
b10000 z
b10000 !"
b10000 $"
1'
#60000
0'
#65000
b110 .
b110 ^
b110 s
b110 A
b110 W
b110 d
b110 i
b110 ,
b110 x
b110 a
b110 f
b11000 {
b11000 #"
1J
b110 1
b110 ]
b110 r
b110 5
b110 [
b110 p
b110 ;
b110 &"
b110 c
b110 o
0/
00
1?
b0 3
b0 U
b0 _
b0 t
b11000000000001100010011 :
b11000000000001100010011 b
b11000000000001100010011 n
b11000000000001100010011 |
b11000000000001100010011 ~
b11000000000001100010011 %"
b101 %
b101 P
b101 !
b101 L
b101 &
b101 K
b11000 y
b11010 @
b11010 w
b11000 6
b10100 7
b10100 z
b10100 !"
b10100 $"
1'
#70000
0'
#75000
b111 .
b111 ^
b111 s
b111 A
b111 W
b111 d
b111 i
b111 a
b111 f
b11100 {
b11100 #"
1J
b111 1
b111 ]
b111 r
b111 5
b111 [
b111 p
b111 c
b111 o
b111 ;
b111 &"
0/
00
1?
b0 3
b0 U
b0 _
b0 t
b11100000000001110010011 :
b11100000000001110010011 b
b11100000000001110010011 n
b11100000000001110010011 |
b11100000000001110010011 ~
b11100000000001110010011 %"
b110 %
b110 P
b110 !
b110 L
b110 &
b110 K
b11100 y
b11111 @
b11111 w
b11100 6
b11000 7
b11000 z
b11000 !"
b11000 $"
1'
#80000
0'
#85000
b1000 .
b1000 ^
b1000 s
b1000 A
b1000 W
b1000 d
b1000 i
b1000 ,
b1000 x
b1000 a
b1000 f
b100000 {
b100000 #"
1J
b1000 1
b1000 ]
b1000 r
b1000 5
b1000 [
b1000 p
b1000 ;
b1000 &"
b1000 c
b1000 o
0/
00
1?
b0 3
b0 U
b0 _
b0 t
b100000000000010000010011 :
b100000000000010000010011 b
b100000000000010000010011 n
b100000000000010000010011 |
b100000000000010000010011 ~
b100000000000010000010011 %"
b111 %
b111 P
b111 !
b111 L
b111 &
b111 K
b100000 y
b100100 @
b100100 w
b100000 6
b11100 7
b11100 z
b11100 !"
b11100 $"
1'
#90000
0'
#95000
b101 .
b101 ^
b101 s
0-
b101 A
b101 W
b101 d
b101 i
b1 4
b1 `
b1 h
b1 u
b1001 e
b1001 g
b1001 m
0G
1B
b10 H
b10 T
b10 X
b10 j
b101 a
b101 f
b0 ,
b0 x
b100100 {
b100100 #"
0J
b101 1
b101 ]
b101 r
b1 2
b1 \
b1 q
b1001 5
b1001 [
b1001 p
b1 =
b1 R
b1 Z
b1 l
b110011 8
b110011 S
b0 c
b0 o
b0 ;
b0 &"
1/
10
0?
b101 3
b101 U
b101 _
b101 t
b10010100001000010010110011 :
b10010100001000010010110011 b
b10010100001000010010110011 n
b10010100001000010010110011 |
b10010100001000010010110011 ~
b10010100001000010010110011 %"
b1000 %
b1000 P
b1000 !
b1000 L
b1000 &
b1000 K
b100100 y
b100000 @
b100000 w
b100100 6
b100000 7
b100000 z
b100000 !"
b100000 $"
1'
#100000
0'
#105000
b1110 .
b1110 ^
b1110 s
b111 a
b111 f
b10 ,
b10 x
b1110 A
b1110 W
b1110 d
b1110 i
b111 3
b111 U
b111 _
b111 t
b10 4
b10 `
b10 h
b10 u
b101000 {
b101000 #"
b111 1
b111 ]
b111 r
b10 2
b10 \
b10 q
b1010 5
b1010 [
b1010 p
b10011100010000010100110011 :
b10011100010000010100110011 b
b10011100010000010100110011 n
b10011100010000010100110011 |
b10011100010000010100110011 ~
b10011100010000010100110011 %"
b1001 %
b1001 P
b1 $
b1 O
b1001 !
b1001 L
b1001 &
b1001 K
b101000 y
b100100 @
b100100 w
b101000 6
b100100 7
b100100 z
b100100 !"
b100100 $"
1'
#110000
0'
#115000
b10011 .
b10011 ^
b10011 s
b1110 a
b1110 f
b100 ,
b100 x
b10011 A
b10011 W
b10011 d
b10011 i
b1110 3
b1110 U
b1110 _
b1110 t
b101 4
b101 `
b101 h
b101 u
b10 e
b10 g
b10 m
b101100 {
b101100 #"
b1010 1
b1010 ]
b1010 r
b1001 2
b1001 \
b1001 q
b1011 5
b1011 [
b1011 p
b0 =
b0 R
b0 Z
b0 l
b101001001000010110110011 :
b101001001000010110110011 b
b101001001000010110110011 n
b101001001000010110110011 |
b101001001000010110110011 ~
b101001001000010110110011 %"
b1010 %
b1010 P
b10 $
b10 O
b1010 !
b1010 L
b1010 &
b1010 K
b101100 y
b101000 @
b101000 w
b101100 6
b101000 7
b101000 z
b101000 !"
b101000 $"
1'
#120000
0'
#125000
b110 .
b110 ^
b110 s
b110 a
b110 f
b0 ,
b0 x
b110 A
b110 W
b110 d
b110 i
b110 3
b110 U
b110 _
b110 t
b1 4
b1 `
b1 h
b1 u
b1001 e
b1001 g
b1001 m
b110000 {
b110000 #"
b110 1
b110 ]
b110 r
b1 2
b1 \
b1 q
b1001 5
b1001 [
b1001 p
b1 =
b1 R
b1 Z
b1 l
b10011000001000010010110011 :
b10011000001000010010110011 b
b10011000001000010010110011 n
b10011000001000010010110011 |
b10011000001000010010110011 ~
b10011000001000010010110011 %"
b1011 %
b1011 P
b11 $
b11 O
b1011 !
b1011 L
b1011 &
b1011 K
b110000 y
b101100 @
b101100 w
b110000 6
b101100 7
b101100 z
b101100 !"
b101100 $"
1'
#130000
0'
#135000
b10000 .
b10000 ^
b10000 s
b1000 a
b1000 f
b10 ,
b10 x
b10000 A
b10000 W
b10000 d
b10000 i
b1000 3
b1000 U
b1000 _
b1000 t
b10 4
b10 `
b10 h
b10 u
b110100 {
b110100 #"
b1000 1
b1000 ]
b1000 r
b10 2
b10 \
b10 q
b1010 5
b1010 [
b1010 p
b10100000010000010100110011 :
b10100000010000010100110011 b
b10100000010000010100110011 n
b10100000010000010100110011 |
b10100000010000010100110011 ~
b10100000010000010100110011 %"
b1100 %
b1100 P
b100 $
b100 O
b1100 !
b1100 L
b1100 &
b1100 K
b110100 y
b110000 @
b110000 w
b110100 6
b110000 7
b110000 z
b110000 !"
b110000 $"
1'
#140000
0'
