src/alu.v
module alu (
    input wire [31:0] a, b,
    input wire [3:0] alu_control,
    output reg [31:0] result,
    output wire zero
);

    assign zero = (result == 0);

    always @(*) begin
        case (alu_control)
            4'b0000: result = a & b;                     // AND
            4'b0001: result = a | b;                     // OR
            4'b0010: result = a + b;                     // ADD
            4'b0110: result = a - b;                     // SUB
            4'b0011: result = a ^ b;                     // XOR
            4'b0100: result = a << b[4:0];               // SLL
            4'b0101: result = a >> b[4:0];               // SRL
            4'b1101: result = $signed(a) >>> b[4:0];     // SRA
            4'b0111: result = ($signed(a) < $signed(b)) ? 1 : 0; // SLT
            4'b1000: result = (a < b) ? 1 : 0;           // SLTU
            default: result = 0;
        endcase
    end
endmodule

src/imm_gen.v
module imm_gen (
    input wire [31:0] instr,
    output reg [31:0] imm_out
);
    always @(*) begin
        case (instr[6:0])
            7'b0010011, // I-type ALU
            7'b0000011, // Loads
            7'b1100111: // JALR
                imm_out = {{20{instr[31]}}, instr[31:20]};
            7'b0100011: // S-type stores
                imm_out = {{20{instr[31]}}, instr[31:25], instr[11:7]};
            7'b1100011: // B-type branches
                imm_out = {{19{instr[31]}}, instr[31], instr[7], instr[30:25], instr[11:8], 1'b0};
            7'b0110111, // LUI
            7'b0010111: // AUIPC
                imm_out = {instr[31:12], 12'b0};
            7'b1101111: // J-type JAL
                imm_out = {{11{instr[31]}}, instr[31], instr[19:12], instr[20], instr[30:21], 1'b0};
            default:
                imm_out = 32'b0;
        endcase
    end
endmodule

accel_cpu/src/alu_control.v
module alu_control (
    input wire [1:0] ALUOp,
    input wire [2:0] funct3,
    input wire [6:0] funct7,
    output reg [3:0] alu_control
);
    always @(*) begin
        case (ALUOp)
            2'b00: alu_control = 4'b0010;  // lw, sw → ADD
            2'b01: alu_control = 4'b0110;  // branch → SUB
            2'b10: begin  // R-type
                case ({funct7, funct3})
                    10'b0000000_000: alu_control = 4'b0010; // ADD
                    10'b0100000_000: alu_control = 4'b0110; // SUB
                    10'b0000000_001: alu_control = 4'b0100; // SLL
                    10'b0000000_010: alu_control = 4'b0111; // SLT
                    10'b0000000_011: alu_control = 4'b1000; // SLTU
                    10'b0000000_100: alu_control = 4'b0011; // XOR
                    10'b0000000_101: alu_control = 4'b0101; // SRL
                    10'b0100000_101: alu_control = 4'b1101; // SRA
                    10'b0000000_110: alu_control = 4'b0001; // OR
                    10'b0000000_111: alu_control = 4'b0000; // AND
                    10'b0000001_000: alu_control = 4'b1001; // MUL
                    default: alu_control = 4'b1111; // INVALID
                endcase
            end
            2'b11: begin  // I-type ALU ops
                case (funct3)
                    3'b000: alu_control = 4'b0010; // ADDI
                    3'b010: alu_control = 4'b0111; // SLTI
                    3'b011: alu_control = 4'b1000; // SLTIU
                    3'b100: alu_control = 4'b0011; // XORI
                    3'b110: alu_control = 4'b0001; // ORI
                    3'b111: alu_control = 4'b0000; // ANDI
                    3'b001: alu_control = 4'b0100; // SLLI
                    3'b101: alu_control = (funct7[5]) ? 4'b1101 : 4'b0101; // SRAI / SRLI
                    default: alu_control = 4'b1111;
                endcase
            end
            default: alu_control = 4'b1111;
        endcase
    end
endmodule

src/regfile.v
module regfile (
    input wire clk,
    input wire reset,
    input wire we,                         // Write enable
    input wire [4:0] rs1, rs2, rd,         // Register addresses
    input wire [31:0] wd,                  // Write data
    output wire [31:0] rd1, rd2            // Read data outputs
);
    reg [31:0] regs [0:31];

    // Read (asynchronous)
    assign rd1 = (rs1 == 0) ? 0 : regs[rs1];
    assign rd2 = (rs2 == 0) ? 0 : regs[rs2];

    // Write with synchronous reset
    integer i;
    always @(posedge clk) begin
        if (reset) begin
            for (i = 0; i < 32; i = i + 1)
                regs[i] <= 0;
        end else if (we && (rd != 0)) begin
            regs[rd] <= wd;
        end
    end
endmodule

base_cpu/src/execute.v
module execute (
    input wire clk,
    input wire reset,
    input wire we,                     // Write enable for register file
    input wire [1:0] alu_op,          // ALUOp from control unit
    input wire [4:0] rs1, rs2, rd,    // Register addresses
    input wire [31:0] instr,          // Full instruction for immediate generation
    input wire alu_src,               // Select between register or immediate
    input wire [2:0] funct3,
    input wire [6:0] funct7,
    input wire [31:0] wb_data,        // Data to write back to register file
    output wire [31:0] alu_result,
    output wire zero,
    output wire [31:0] rd1, rd2
);

    wire [31:0] op2;
    wire [3:0] alu_control;
    wire [31:0] imm;

    // Register file
    regfile rf (
        .clk(clk),
        .reset(reset),
        .we(we),
        .rs1(rs1),
        .rs2(rs2),
        .rd(rd),
        .wd(wb_data),
        .rd1(rd1),
        .rd2(rd2)
    );

    // ALU control
    alu_control alu_ctl (
        .ALUOp(alu_op),
        .funct3(funct3),
        .funct7(funct7),
        .alu_control(alu_control)
    );

    // Immediate generator
    imm_gen imm_generator (
        .instr(instr),
        .imm_out(imm)
    );

    // ALU second operand selection
    assign op2 = (alu_src) ? imm : rd2;

    // ALU
    alu alu_core (
        .a(rd1),
        .b(op2),
        .alu_control(alu_control),
        .result(alu_result),
        .zero(zero)
    );

endmodule

base_cpu/src/data_mem.v
module data_mem(
    input wire clk,
    input wire mem_read,
    input wire mem_write,
    input wire [31:0] addr,
    input wire [31:0] write_data,
    output wire [31:0] read_data
);
    reg [31:0] mem [0:255];

    initial begin
        // Optionally pre-load memory from file
    end

    always @(posedge clk) begin
        if (mem_write) begin
            mem[addr[9:2]] <= write_data;
        end
    end

    assign read_data = mem_read ? mem[addr[9:2]] : 32'b0;
endmodule

base_cpu/src/control_unit.v
module control_unit(
    input  wire [6:0] opcode,
    input  wire [2:0] funct3,
    input  wire [6:0] funct7,
    output reg  [1:0] ALUOp,
    output reg  RegWrite,
    output reg  MemRead,
    output reg  MemWrite,
    output reg  Branch,
    output reg  Jump,
    output reg  ALUSrc
);

    always @(*) begin
        // Default values
        ALUOp    = 2'b00;
        RegWrite = 0;
        MemRead  = 0;
        MemWrite = 0;
        Branch   = 0;
        Jump     = 0;
        ALUSrc   = 0;

        case (opcode)
            7'b0110011: begin // R-type
                RegWrite = 1;
                ALUOp    = 2'b10;
                ALUSrc   = 0;
            end
            7'b0010011: begin // I-type ALU
                RegWrite = 1;
                ALUOp    = 2'b11;
                ALUSrc   = 1;
            end
            7'b0000011: begin // Load
                RegWrite = 1;
                MemRead  = 1;
                ALUOp    = 2'b00;
                ALUSrc   = 1;
            end
            7'b0100011: begin // Store
                MemWrite = 1;
                ALUOp    = 2'b00;
                ALUSrc   = 1;
            end
            7'b1100011: begin // Branch
                Branch   = 1;
                ALUOp    = 2'b01;
                ALUSrc   = 0;
            end
            7'b1101111: begin // JAL
                Jump     = 1;
                RegWrite = 1;
            end
            7'b1100111: begin // JALR
                Jump     = 1;
                RegWrite = 1;
                ALUSrc   = 1;
                ALUOp    = 2'b00;
            end
            default: begin
            end
        endcase
    end
endmodule

src/instr_mem.v
module instr_mem #(
    parameter INIT_FILE = "program.mem"
) (
    input wire [31:0] addr,
    output wire [31:0] instr
);
    reg [31:0] mem [0:255];  // 1KB instruction memory (256 words)

    initial begin
        $readmemh(INIT_FILE, mem);  // Load instructions from hex file
    end

    assign instr = mem[addr[9:2]];  // Word-aligned address (ignore bottom 2 bits)
endmodule

accel_cpu/src/pc.v
module pc(
    input wire clk,
    input wire reset,
    input wire [31:0] next_pc,
    output reg [31:0] pc_out
);
    always @(posedge clk or posedge reset) begin
        if (reset)
            pc_out <= 32'h00000000;
        else
            pc_out <= next_pc;
    end
endmodule

src/cpu_fetch.v
module cpu_fetch #(
    parameter MEMFILE = "program.mem"
) (
    input  wire        clk,
    input  wire        reset,

    // Control signals / targets
    input  wire        jal,            // jal instruction
    input  wire        jalr,           // jalr instruction
    input  wire        branch,         // conditional branch instruction
    input  wire        branch_taken,   // result of branch comparison from ALU
    input  wire [31:0] branch_target,  // PC-relative target for jal/branch
    input  wire [31:0] jalr_target,    // Target address for jalr

    output wire [31:0] instr,
    output wire [31:0] pc_out
);
    wire [31:0] next_pc;

    // Program Counter instance
    pc pc_inst (
        .clk(clk),
        .reset(reset),
        .next_pc(next_pc),
        .pc_out(pc_out)
    );

    // Instruction Memory instance
    instr_mem #(.INIT_FILE(MEMFILE)) imem (
        .addr(pc_out),
        .instr(instr)
    );

    // Next PC generation with branch/jump handling
    wire [31:0] pc_plus4 = pc_out + 4;

    assign next_pc = jal  ? branch_target :
                     jalr ? jalr_target  :
                     (branch && branch_taken) ? branch_target :
                     pc_plus4;

endmodule

base_cpu/src/cpu.v
module cpu #(
    parameter MEMFILE = "program.mem"
) (
    input wire clk,
    input wire reset,
    output reg [31:0] cycle_count
);
    wire [31:0] instr;
    wire [31:0] pc_out;

    // Performance counters
    reg [31:0] instr_count;
    reg [31:0] mem_read_count;
    reg [31:0] mem_write_count;
    reg [31:0] rf_read_count;
    reg [31:0] rf_write_count;

    // Signals for fetch stage
    wire jal, jalr;
    wire branch_taken;
    wire [31:0] branch_target, jalr_target;

    cpu_fetch #(.MEMFILE(MEMFILE)) fetch_unit(
        .clk(clk),
        .reset(reset),
        .jal(jal),
        .jalr(jalr),
        .branch(Branch),
        .branch_taken(branch_taken),
        .branch_target(branch_target),
        .jalr_target(jalr_target),
        .instr(instr),
        .pc_out(pc_out)
    );

    // Decode fields
    wire [6:0] opcode = instr[6:0];
    wire [2:0] funct3 = instr[14:12];
    wire [6:0] funct7 = instr[31:25];

    // Halt detection (using the EBREAK instruction)
    wire halt = (instr == 32'h0010_0073);
    wire [4:0] rd  = instr[11:7];
    wire [4:0] rs1 = instr[19:15];
    wire [4:0] rs2 = instr[24:20];

    // Immediate generator
    wire [31:0] imm;
    imm_gen imm_unit(
        .instr(instr),
        .imm_out(imm)
    );

    // Control signals
    wire [1:0] ALUOp;
    wire RegWrite, MemRead, MemWrite, Branch, Jump, ALUSrc;

    control_unit cu(
        .opcode(opcode),
        .funct3(funct3),
        .funct7(funct7),
        .ALUOp(ALUOp),
        .RegWrite(RegWrite),
        .MemRead(MemRead),
        .MemWrite(MemWrite),
        .Branch(Branch),
        .Jump(Jump),
        .ALUSrc(ALUSrc)
    );

    // Register and ALU outputs
    wire [31:0] alu_result;
    wire zero;
    wire [31:0] rd1, rd2;
    wire [31:0] write_back_data;

    // Data memory
    wire [31:0] mem_data;
    data_mem dmem(
        .clk(clk),
        .mem_read(MemRead),
        .mem_write(MemWrite),
        .addr(alu_result),
        .write_data(rd2),
        .read_data(mem_data)
    );


    execute exec_unit(
        .clk(clk),
        .reset(reset),
        .we(RegWrite),
        .alu_op(ALUOp),
        .rs1(rs1),
        .rs2(rs2),
        .rd(rd),
        .instr(instr),
        .alu_src(ALUSrc),
        .funct3(funct3),
        .funct7(funct7),
        .wb_data(write_back_data),
        .alu_result(alu_result),
        .zero(zero),
        .rd1(rd1),
        .rd2(rd2)
    );

    // PC increment
    wire [31:0] pc_plus4 = pc_out + 4;

    // Branch and jump target calculations
    assign branch_target = pc_out + imm;
    assign jalr_target   = (rd1 + imm) & 32'hffff_fffe;

    // Branch comparison helpers
    wire eq      = (rd1 == rd2);
    wire slt     = ($signed(rd1) < $signed(rd2));
    wire sltu    = (rd1 < rd2);

    // Branch decision based on funct3
    reg branch_cond;
    always @(*) begin
        case (funct3)
            3'b000: branch_cond = eq;          // BEQ
            3'b001: branch_cond = !eq;         // BNE
            3'b100: branch_cond = slt;         // BLT
            3'b101: branch_cond = !slt;        // BGE
            3'b110: branch_cond = sltu;        // BLTU
            3'b111: branch_cond = !sltu;       // BGEU
            default: branch_cond = 1'b0;
        endcase
    end

    assign branch_taken = Branch && branch_cond;

    // Distinguish between JAL and JALR
    assign jal  = Jump && (opcode == 7'b1101111);
    assign jalr = Jump && (opcode == 7'b1100111);

    // Writeback mux: priority Jump -> Load -> ALU
    assign write_back_data = jal | jalr ? pc_plus4 :
                              MemRead    ? mem_data  :
                              alu_result;

    // Cycle counter and other performance metrics
    always @(posedge clk) begin
        if (reset) begin
            cycle_count     <= 0;
            instr_count     <= 0;
            mem_read_count  <= 0;
            mem_write_count <= 0;
            rf_read_count   <= 0;
            rf_write_count  <= 0;
        end else if (!halt) begin
            cycle_count <= cycle_count + 1;
            instr_count <= instr_count + 1;

            // Memory access counters
            if (MemRead)
                mem_read_count <= mem_read_count + 1;
            if (MemWrite)
                mem_write_count <= mem_write_count + 1;

            // Register file read counters
            if ((opcode != 7'b1101111) && (rs1 != 0))
                rf_read_count <= rf_read_count + 1;
            if ((opcode == 7'b0110011 || opcode == 7'b0100011 || opcode == 7'b1100011) && (rs2 != 0))
                rf_read_count <= rf_read_count + 1;

            // Register file write counter
            if (RegWrite && rd != 0)
                rf_write_count <= rf_write_count + 1;
        end
    end

    // TODO: Power estimation hooks can be added for FPGA implementation
endmodule

base_cpu/testbench/cpu_program_tb.v
`timescale 1ns / 1ps

module cpu_program_tb;
    reg clk = 0;
    reg reset;
    wire [31:0] cycle_count;

    cpu #(.MEMFILE("program.mem")) uut (
        .clk(clk),
        .reset(reset),
        .cycle_count(cycle_count)
    );

    always #5 clk = ~clk;

    initial begin
        $dumpfile("sim/cpu_program_tb.vcd");
        $dumpvars(0, cpu_program_tb);
        $display("=== Base CPU program.mem Test ===");

        reset = 1;
        @(posedge clk); @(posedge clk); reset = 0;

        repeat(50) @(posedge clk); #1;
        $display("ReLU(-1) = %0d", uut.exec_unit.rf.regs[2]);
        $display("ReLU(+5) = %0d", uut.exec_unit.rf.regs[4]);
        $display("Dot product = %0d", uut.exec_unit.rf.regs[7]);
        $display("MatMul results: %0d %0d %0d %0d",
                 uut.exec_unit.rf.regs[12], uut.exec_unit.rf.regs[13],
                 uut.exec_unit.rf.regs[14], uut.exec_unit.rf.regs[15]);
        $display("Cycles: %0d", cycle_count);
        $finish;
    end
endmodule

base_cpu/sim/cpu_program_tb.vcd
$date
	Tue Jul  1 02:26:54 2025
$end
$version
	Icarus Verilog
$end
$timescale
	1ps
$end
$scope module cpu_program_tb $end
$var wire 32 ! cycle_count [31:0] $end
$var reg 1 " clk $end
$var reg 1 # reset $end
$scope module uut $end
$var wire 1 $ branch_taken $end
$var wire 1 " clk $end
$var wire 1 % jal $end
$var wire 1 & jalr $end
$var wire 32 ' jalr_target [31:0] $end
$var wire 1 # reset $end
$var wire 1 ( zero $end
$var wire 32 ) write_back_data [31:0] $end
$var wire 1 * sltu $end
$var wire 1 + slt $end
$var wire 5 , rs2 [4:0] $end
$var wire 5 - rs1 [4:0] $end
$var wire 32 . rd2 [31:0] $end
$var wire 32 / rd1 [31:0] $end
$var wire 5 0 rd [4:0] $end
$var wire 32 1 pc_plus4 [31:0] $end
$var wire 32 2 pc_out [31:0] $end
$var wire 7 3 opcode [6:0] $end
$var wire 32 4 mem_data [31:0] $end
$var wire 32 5 instr [31:0] $end
$var wire 32 6 imm [31:0] $end
$var wire 1 7 halt $end
$var wire 7 8 funct7 [6:0] $end
$var wire 3 9 funct3 [2:0] $end
$var wire 1 : eq $end
$var wire 32 ; branch_target [31:0] $end
$var wire 32 < alu_result [31:0] $end
$var wire 1 = RegWrite $end
$var wire 1 > MemWrite $end
$var wire 1 ? MemRead $end
$var wire 1 @ Jump $end
$var wire 1 A Branch $end
$var wire 1 B ALUSrc $end
$var wire 2 C ALUOp [1:0] $end
$var parameter 88 D MEMFILE $end
$var reg 1 E branch_cond $end
$var reg 32 F cycle_count [31:0] $end
$var reg 32 G instr_count [31:0] $end
$var reg 32 H mem_read_count [31:0] $end
$var reg 32 I mem_write_count [31:0] $end
$var reg 32 J rf_read_count [31:0] $end
$var reg 32 K rf_write_count [31:0] $end
$scope module cu $end
$var wire 3 L funct3 [2:0] $end
$var wire 7 M funct7 [6:0] $end
$var wire 7 N opcode [6:0] $end
$var reg 2 O ALUOp [1:0] $end
$var reg 1 B ALUSrc $end
$var reg 1 A Branch $end
$var reg 1 @ Jump $end
$var reg 1 ? MemRead $end
$var reg 1 > MemWrite $end
$var reg 1 = RegWrite $end
$upscope $end
$scope module dmem $end
$var wire 1 " clk $end
$var wire 1 ? mem_read $end
$var wire 1 > mem_write $end
$var wire 32 P write_data [31:0] $end
$var wire 32 Q read_data [31:0] $end
$var wire 32 R addr [31:0] $end
$upscope $end
$scope module exec_unit $end
$var wire 2 S alu_op [1:0] $end
$var wire 1 B alu_src $end
$var wire 1 " clk $end
$var wire 3 T funct3 [2:0] $end
$var wire 7 U funct7 [6:0] $end
$var wire 5 V rd [4:0] $end
$var wire 1 # reset $end
$var wire 5 W rs1 [4:0] $end
$var wire 5 X rs2 [4:0] $end
$var wire 32 Y wb_data [31:0] $end
$var wire 1 = we $end
$var wire 1 ( zero $end
$var wire 32 Z rd2 [31:0] $end
$var wire 32 [ rd1 [31:0] $end
$var wire 32 \ op2 [31:0] $end
$var wire 32 ] instr [31:0] $end
$var wire 32 ^ imm [31:0] $end
$var wire 32 _ alu_result [31:0] $end
$var wire 4 ` alu_control [3:0] $end
$scope module alu_core $end
$var wire 32 a b [31:0] $end
$var wire 1 ( zero $end
$var wire 4 b alu_control [3:0] $end
$var wire 32 c a [31:0] $end
$var reg 32 d result [31:0] $end
$upscope $end
$scope module alu_ctl $end
$var wire 2 e ALUOp [1:0] $end
$var wire 3 f funct3 [2:0] $end
$var wire 7 g funct7 [6:0] $end
$var reg 4 h alu_control [3:0] $end
$upscope $end
$scope module imm_generator $end
$var wire 32 i instr [31:0] $end
$var reg 32 j imm_out [31:0] $end
$upscope $end
$scope module rf $end
$var wire 1 " clk $end
$var wire 5 k rd [4:0] $end
$var wire 1 # reset $end
$var wire 5 l rs1 [4:0] $end
$var wire 5 m rs2 [4:0] $end
$var wire 32 n wd [31:0] $end
$var wire 1 = we $end
$var wire 32 o rd2 [31:0] $end
$var wire 32 p rd1 [31:0] $end
$var integer 32 q i [31:0] $end
$upscope $end
$upscope $end
$scope module fetch_unit $end
$var wire 1 A branch $end
$var wire 1 $ branch_taken $end
$var wire 32 r branch_target [31:0] $end
$var wire 1 " clk $end
$var wire 1 % jal $end
$var wire 1 & jalr $end
$var wire 32 s jalr_target [31:0] $end
$var wire 1 # reset $end
$var wire 32 t pc_plus4 [31:0] $end
$var wire 32 u pc_out [31:0] $end
$var wire 32 v next_pc [31:0] $end
$var wire 32 w instr [31:0] $end
$var parameter 88 x MEMFILE $end
$scope module imem $end
$var wire 32 y instr [31:0] $end
$var wire 32 z addr [31:0] $end
$var parameter 88 { INIT_FILE $end
$upscope $end
$scope module pc_inst $end
$var wire 1 " clk $end
$var wire 32 | next_pc [31:0] $end
$var wire 1 # reset $end
$var reg 32 } pc_out [31:0] $end
$upscope $end
$upscope $end
$scope module imm_unit $end
$var wire 32 ~ instr [31:0] $end
$var reg 32 !" imm_out [31:0] $end
$upscope $end
$upscope $end
$upscope $end
$enddefinitions $end
$comment Show the parameter values. $end
$dumpall
b111000001110010011011110110011101110010011000010110110100101110011011010110010101101101 {
b111000001110010011011110110011101110010011000010110110100101110011011010110010101101101 x
b111000001110010011011110110011101110010011000010110110100101110011011010110010101101101 D
$end
#0
$dumpvars
b11111111111111111111111111111111 !"
b11111111111100000000000010010011 ~
b0 }
b100 |
b0 z
b11111111111100000000000010010011 y
b11111111111100000000000010010011 w
b100 v
b0 u
b100 t
b11111111111111111111111111111110 s
b11111111111111111111111111111111 r
bx q
b0 p
bx o
b11111111111111111111111111111111 n
b11111 m
b0 l
b1 k
b11111111111111111111111111111111 j
b11111111111100000000000010010011 i
b10 h
b1111111 g
b0 f
b11 e
b11111111111111111111111111111111 d
b0 c
b10 b
b11111111111111111111111111111111 a
b10 `
b11111111111111111111111111111111 _
b11111111111111111111111111111111 ^
b11111111111100000000000010010011 ]
b11111111111111111111111111111111 \
b0 [
bx Z
b11111111111111111111111111111111 Y
b11111 X
b0 W
b1 V
b1111111 U
b0 T
b11 S
b11111111111111111111111111111111 R
b0 Q
bx P
b11 O
b10011 N
b1111111 M
b0 L
bx K
bx J
bx I
bx H
bx G
bx F
xE
b11 C
1B
0A
0@
0?
0>
1=
b11111111111111111111111111111111 <
b11111111111111111111111111111111 ;
x:
b0 9
b1111111 8
07
b11111111111111111111111111111111 6
b11111111111100000000000010010011 5
b0 4
b10011 3
b0 2
b100 1
b1 0
b0 /
bx .
b0 -
b11111 ,
x+
x*
b11111111111111111111111111111111 )
0(
b11111111111111111111111111111110 '
0&
0%
0$
1#
0"
bx !
$end
#5000
1E
0*
0+
1:
b0 .
b0 P
b0 Z
b0 o
b0 K
b0 J
b0 I
b0 H
b0 G
b0 !
b0 F
b100000 q
1"
#10000
0"
#15000
0#
b100000 q
1"
#20000
0"
#25000
0E
1+
0:
b11111111111111111111111111111111 /
b11111111111111111111111111111111 [
b11111111111111111111111111111111 c
b11111111111111111111111111111111 p
b1101 `
b1101 b
b1101 h
b10000011110 '
b10000011110 s
b10000011111 \
b10000011111 a
b1000 v
b1000 |
b1 -
b1 W
b1 l
b10 0
b10 V
b10 k
b100000 8
b100000 M
b100000 U
b100000 g
b101 9
b101 L
b101 T
b101 f
b10000011111 6
b10000011111 !"
b10000011111 ^
b10000011111 j
b1000001111100001101000100010011 5
b1000001111100001101000100010011 ]
b1000001111100001101000100010011 i
b1000001111100001101000100010011 w
b1000001111100001101000100010011 y
b1000001111100001101000100010011 ~
b1 K
b1 G
b1 !
b1 F
b1000 t
b10000100011 ;
b10000100011 r
b1000 1
b100 2
b100 u
b100 z
b100 }
1"
#30000
0"
#35000
b0 )
b0 Y
b0 n
1(
b0 <
b0 R
b0 _
b0 d
b11 `
b11 b
b11 h
1E
b11111111111111111111111111111111 \
b11111111111111111111111111111111 a
b11111111111111111111111111111110 '
b11111111111111111111111111111110 s
b1100 v
b1100 |
b10 -
b10 W
b10 l
b1111111 8
b1111111 M
b1111111 U
b1111111 g
b100 9
b100 L
b100 T
b100 f
b11111111111111111111111111111111 ^
b11111111111111111111111111111111 j
b11111111111111111111111111111111 6
b11111111111111111111111111111111 !"
b11111111111100010100000100010011 5
b11111111111100010100000100010011 ]
b11111111111100010100000100010011 i
b11111111111100010100000100010011 w
b11111111111100010100000100010011 y
b11111111111100010100000100010011 ~
b10 K
b1 J
b10 G
b10 !
b10 F
b1100 t
b111 ;
b111 r
b1100 1
b1000 2
b1000 u
b1000 z
b1000 }
1"
#40000
0"
#45000
b0 )
b0 Y
b0 n
b0 `
b0 b
b0 h
0B
1=
b10 C
b10 O
b10 S
b10 e
b0 \
b0 a
b10000 v
b10000 |
b11111111111111111111111111111110 '
b11111111111111111111111111111110 s
1(
b0 <
b0 R
b0 _
b0 d
b10 ,
b10 X
b10 m
b1 -
b1 W
b1 l
b0 8
b0 M
b0 U
b0 g
b111 9
b111 L
b111 T
b111 f
b110011 3
b110011 N
b0 6
b0 !"
b0 ^
b0 j
1+
0:
b11111111111111111111111111111111 /
b11111111111111111111111111111111 [
b11111111111111111111111111111111 c
b11111111111111111111111111111111 p
b1000001111000100110011 5
b1000001111000100110011 ]
b1000001111000100110011 i
b1000001111000100110011 w
b1000001111000100110011 y
b1000001111000100110011 ~
b11 K
b10 J
b11 G
b11 !
b11 F
b10000 t
b1100 ;
b1100 r
b10000 1
b1100 2
b1100 u
b1100 z
b1100 }
1"
#50000
0"
#55000
b101 )
b101 Y
b101 n
0(
b101 <
b101 R
b101 _
b101 d
b101 \
b101 a
0+
1:
b0 /
b0 [
b0 c
b0 p
b10 `
b10 b
b10 h
1E
1B
1=
b11 C
b11 O
b11 S
b11 e
b100 '
b100 s
b10100 v
b10100 |
b101 ,
b101 X
b101 m
b0 -
b0 W
b0 l
b11 0
b11 V
b11 k
b0 9
b0 L
b0 T
b0 f
b10011 3
b10011 N
b101 ^
b101 j
b101 6
b101 !"
b10100000000000110010011 5
b10100000000000110010011 ]
b10100000000000110010011 i
b10100000000000110010011 w
b10100000000000110010011 y
b10100000000000110010011 ~
b100 K
b11 J
b100 G
b100 !
b100 F
b10100 t
b10101 ;
b10101 r
b10100 1
b10000 2
b10000 u
b10000 z
b10000 }
1"
#60000
0"
#65000
b0 )
b0 Y
b0 n
1(
b0 <
b0 R
b0 _
b0 d
0:
b101 /
b101 [
b101 c
b101 p
b1101 `
b1101 b
b1101 h
b10000100100 '
b10000100100 s
b10000011111 \
b10000011111 a
b11000 v
b11000 |
b11111 ,
b11111 X
b11111 m
b11 -
b11 W
b11 l
b100 0
b100 V
b100 k
b100000 8
b100000 M
b100000 U
b100000 g
b101 9
b101 L
b101 T
b101 f
b10000011111 6
b10000011111 !"
b10000011111 ^
b10000011111 j
b1000001111100011101001000010011 5
b1000001111100011101001000010011 ]
b1000001111100011101001000010011 i
b1000001111100011101001000010011 w
b1000001111100011101001000010011 y
b1000001111100011101001000010011 ~
b101 K
b101 G
b101 !
b101 F
b11000 t
b10000110011 ;
b10000110011 r
b11000 1
b10100 2
b10100 u
b10100 z
b10100 }
1"
#70000
0"
#75000
b11111111111111111111111111111010 )
b11111111111111111111111111111010 Y
b11111111111111111111111111111010 n
0(
b11111111111111111111111111111010 <
b11111111111111111111111111111010 R
b11111111111111111111111111111010 _
b11111111111111111111111111111010 d
b11 `
b11 b
b11 h
0E
b11111111111111111111111111111111 \
b11111111111111111111111111111111 a
b100 '
b100 s
b11100 v
b11100 |
b1111111 8
b1111111 M
b1111111 U
b1111111 g
b100 9
b100 L
b100 T
b100 f
b11111111111111111111111111111111 ^
b11111111111111111111111111111111 j
b11111111111111111111111111111111 6
b11111111111111111111111111111111 !"
b11111111111100011100001000010011 5
b11111111111100011100001000010011 ]
b11111111111100011100001000010011 i
b11111111111100011100001000010011 w
b11111111111100011100001000010011 y
b11111111111100011100001000010011 ~
b110 K
b100 J
b110 G
b110 !
b110 F
b11100 t
b10111 ;
b10111 r
b11100 1
b11000 2
b11000 u
b11000 z
b11000 }
1"
#80000
0"
#85000
b0 )
b0 Y
b0 n
1(
b0 <
b0 R
b0 _
b0 d
1*
b11111111111111111111111111111010 .
b11111111111111111111111111111010 P
b11111111111111111111111111111010 Z
b11111111111111111111111111111010 o
b0 `
b0 b
b0 h
0E
0B
1=
b10 C
b10 O
b10 S
b10 e
b11111111111111111111111111111010 \
b11111111111111111111111111111010 a
b100000 v
b100000 |
b100 ,
b100 X
b100 m
b0 8
b0 M
b0 U
b0 g
b111 9
b111 L
b111 T
b111 f
b110011 3
b110011 N
b0 6
b0 !"
b0 ^
b0 j
b10000011111001000110011 5
b10000011111001000110011 ]
b10000011111001000110011 i
b10000011111001000110011 w
b10000011111001000110011 y
b10000011111001000110011 ~
b111 K
b101 J
b111 G
b111 !
b111 F
b100000 t
b11100 ;
b11100 r
b100000 1
b11100 2
b11100 u
b11100 z
b11100 }
1"
#90000
0"
#95000
b10 )
b10 Y
b10 n
0(
b10 <
b10 R
b10 _
b10 d
1E
1:
b0 /
b0 [
b0 c
b0 p
b10 `
b10 b
b10 h
1B
1=
b11 C
b11 O
b11 S
b11 e
b10 '
b10 s
b100100 v
b100100 |
b10 \
b10 a
b10 ,
b10 X
b10 m
b0 -
b0 W
b0 l
b101 0
b101 V
b101 k
b0 9
b0 L
b0 T
b0 f
b10011 3
b10011 N
b10 ^
b10 j
b10 6
b10 !"
0*
b0 .
b0 P
b0 Z
b0 o
b1000000000001010010011 5
b1000000000001010010011 ]
b1000000000001010010011 i
b1000000000001010010011 w
b1000000000001010010011 y
b1000000000001010010011 ~
b1000 K
b110 J
b1000 G
b1000 !
b1000 F
b100100 t
b100010 ;
b100010 r
b100100 1
b100000 2
b100000 u
b100000 z
b100000 }
1"
#100000
0"
#105000
b11 )
b11 Y
b11 n
0E
b11 <
b11 R
b11 _
b11 d
1*
1+
0:
b101 .
b101 P
b101 Z
b101 o
b11 \
b11 a
b101000 v
b101000 |
b11 ,
b11 X
b11 m
b110 0
b110 V
b110 k
b11 6
b11 !"
b11 ^
b11 j
b1100000000001100010011 5
b1100000000001100010011 ]
b1100000000001100010011 i
b1100000000001100010011 w
b1100000000001100010011 y
b1100000000001100010011 ~
b1001 K
b1001 G
b1001 !
b1001 F
b101000 t
b100111 ;
b100111 r
b101000 1
b100100 2
b100100 u
b100100 z
b100100 }
1"
#110000
0"
#115000
b110000000000000000 )
b110000000000000000 Y
b110000000000000000 n
b110000000000000000 <
b110000000000000000 R
b110000000000000000 _
b110000000000000000 d
0*
0+
b0 .
b0 P
b0 Z
b0 o
b11 /
b11 [
b11 c
b11 p
b100 `
b100 b
b100 h
1E
b10000 \
b10000 a
b10010 '
b10010 s
b101100 v
b101100 |
b10000 ,
b10000 X
b10000 m
b110 -
b110 W
b110 l
b1 9
b1 L
b1 T
b1 f
b10000 ^
b10000 j
b10000 6
b10000 !"
b1000000110001001100010011 5
b1000000110001001100010011 ]
b1000000110001001100010011 i
b1000000110001001100010011 w
b1000000110001001100010011 y
b1000000110001001100010011 ~
b1010 K
b1010 G
b1010 !
b1010 F
b101100 t
b111000 ;
b111000 r
b101100 1
b101000 2
b101000 u
b101000 z
b101000 }
1"
#120000
0"
