src/alu.v
module alu (
    input wire [31:0] a, b,
    input wire [3:0] alu_control,
    output reg [31:0] result,
    output wire zero
);

    assign zero = (result == 0);

    always @(*) begin
        case (alu_control)
            4'b0000: result = a & b;                     // AND
            4'b0001: result = a | b;                     // OR
            4'b0010: result = a + b;                     // ADD
            4'b0110: result = a - b;                     // SUB
            4'b0011: result = a ^ b;                     // XOR
            4'b0100: result = a << b[4:0];               // SLL
            4'b0101: result = a >> b[4:0];               // SRL
            4'b1101: result = $signed(a) >>> b[4:0];     // SRA
            4'b0111: result = ($signed(a) < $signed(b)) ? 1 : 0; // SLT
            4'b1000: result = (a < b) ? 1 : 0;           // SLTU
            default: result = 0;
        endcase
    end
endmodule

base_cpu/testbench/alu_tb.v
`timescale 1ns / 1ps

module alu_tb;

    reg [31:0] a, b;
    reg [3:0] alu_control;
    wire [31:0] result;
    wire zero;

    alu uut (
        .a(a),
        .b(b),
        .alu_control(alu_control),
        .result(result),
        .zero(zero)
    );

    initial begin
        $dumpfile("sim/alu.vcd");
        $dumpvars(0, alu_tb);

        // Test ADD
        a = 10; b = 5; alu_control = 4'b0010; #10;  // ADD: 15
        // Test SUB
        a = 10; b = 5; alu_control = 4'b0110; #10;  // SUB: 5
        // Test AND
        a = 32'hF0F0_F0F0; b = 32'h0F0F_0F0F; alu_control = 4'b0000; #10;  // AND: 0
        // Test OR
        a = 32'hF0F0_0000; b = 32'h0000_0F0F; alu_control = 4'b0001; #10;  // OR
        // Test XOR
        a = 32'hFF00_FF00; b = 32'h00FF_00FF; alu_control = 4'b0011; #10;  // XOR
        // Test SLL
        a = 32'h0000_0001; b = 5; alu_control = 4'b0100; #10;  // SLL: 0x20
        // Test SRL
        a = 32'h0000_0020; b = 5; alu_control = 4'b0101; #10;  // SRL: 1
        // Test SRA
        a = -32'sd32; b = 5; alu_control = 4'b1101; #10;  // SRA: sign-preserved shift
        // Test SLT (signed)
        a = -1; b = 5; alu_control = 4'b0111; #10;  // SLT: 1
        // Test SLTU (unsigned)
        a = 32'h0000_0001; b = 32'hFFFF_FFFF; alu_control = 4'b1000; #10;  // SLTU: 1
        // Test Zero flag
        a = 5; b = 5; alu_control = 4'b0110; #10;  // SUB: 0, zero=1

        $finish;
    end

endmodule

sim/alu.vcd
$date
	Wed May 28 00:57:09 2025
$end
$version
	Icarus Verilog
$end
$timescale
	1ps
$end
$scope module alu_tb $end
$var wire 1 ! zero $end
$var wire 32 " result [31:0] $end
$var reg 32 # a [31:0] $end
$var reg 4 $ alu_control [3:0] $end
$var reg 32 % b [31:0] $end
$scope module uut $end
$var wire 32 & a [31:0] $end
$var wire 4 ' alu_control [3:0] $end
$var wire 32 ( b [31:0] $end
$var wire 1 ! zero $end
$var reg 32 ) result [31:0] $end
$upscope $end
$upscope $end
$enddefinitions $end
$comment Show the parameter values. $end
$dumpall
$end
#0
$dumpvars
b1111 )
b101 (
b10 '
b1010 &
b101 %
b10 $
b1010 #
b1111 "
0!
$end
#10000
b101 "
b101 )
b110 $
b110 '
#20000
1!
b0 "
b0 )
b0 $
b0 '
b1111000011110000111100001111 %
b1111000011110000111100001111 (
b11110000111100001111000011110000 #
b11110000111100001111000011110000 &
#30000
0!
b11110000111100000000111100001111 "
b11110000111100000000111100001111 )
b1 $
b1 '
b111100001111 %
b111100001111 (
b11110000111100000000000000000000 #
b11110000111100000000000000000000 &
#40000
b11111111111111111111111111111111 "
b11111111111111111111111111111111 )
b11 $
b11 '
b111111110000000011111111 %
b111111110000000011111111 (
b11111111000000001111111100000000 #
b11111111000000001111111100000000 &
#50000
b100000 "
b100000 )
b100 $
b100 '
b101 %
b101 (
b1 #
b1 &
#60000
b1 "
b1 )
b101 $
b101 '
b100000 #
b100000 &
#70000
b11111111111111111111111111111111 "
b11111111111111111111111111111111 )
b1101 $
b1101 '
b11111111111111111111111111100000 #
b11111111111111111111111111100000 &
#80000
b1 "
b1 )
b111 $
b111 '
b11111111111111111111111111111111 #
b11111111111111111111111111111111 &
#90000
b1000 $
b1000 '
b11111111111111111111111111111111 %
b11111111111111111111111111111111 (
b1 #
b1 &
#100000
1!
b0 "
b0 )
b110 $
b110 '
b101 %
b101 (
b101 #
b101 &
