src/alu_control.v
module alu_control (
    input wire [1:0] ALUOp,
    input wire [2:0] funct3,
    input wire funct7_5, // bit 30 from funct7
    output reg [3:0] alu_control
);
    always @(*) begin
        case (ALUOp)
            2'b00: alu_control = 4'b0010;  // lw, sw → ADD
            2'b01: alu_control = 4'b0110;  // branch → SUB
            2'b10: begin  // R-type
                case ({funct7_5, funct3})
                    4'b0000: alu_control = 4'b0010; // ADD
                    4'b1000: alu_control = 4'b0110; // SUB
                    4'b0001: alu_control = 4'b0100; // SLL
                    4'b0010: alu_control = 4'b0111; // SLT
                    4'b0011: alu_control = 4'b1000; // SLTU
                    4'b0100: alu_control = 4'b0011; // XOR
                    4'b0101: alu_control = 4'b0101; // SRL
                    4'b1101: alu_control = 4'b1101; // SRA
                    4'b0110: alu_control = 4'b0001; // OR
                    4'b0111: alu_control = 4'b0000; // AND
                    default: alu_control = 4'b1111; // INVALID
                endcase
            end
            2'b11: begin  // I-type ALU ops
                case (funct3)
                    3'b000: alu_control = 4'b0010; // ADDI
                    3'b010: alu_control = 4'b0111; // SLTI
                    3'b011: alu_control = 4'b1000; // SLTIU
                    3'b100: alu_control = 4'b0011; // XORI
                    3'b110: alu_control = 4'b0001; // ORI
                    3'b111: alu_control = 4'b0000; // ANDI
                    3'b001: alu_control = 4'b0100; // SLLI
                    3'b101: alu_control = (funct7_5) ? 4'b1101 : 4'b0101; // SRAI / SRLI
                    default: alu_control = 4'b1111;
                endcase
            end
            default: alu_control = 4'b1111;
        endcase
    end
endmodule

testbench/alu_control_tb.v
`timescale 1ns / 1ps

module alu_control_tb;

    reg [1:0] ALUOp;
    reg [2:0] funct3;
    reg funct7_5;
    wire [3:0] alu_control;

    alu_control uut (
        .ALUOp(ALUOp),
        .funct3(funct3),
        .funct7_5(funct7_5),
        .alu_control(alu_control)
    );

    initial begin
        $dumpfile("sim/alu_control.vcd");
        $dumpvars(0, alu_control_tb);

        // R-type: ADD (funct3 = 000, funct7[5] = 0)
        ALUOp = 2'b10; funct3 = 3'b000; funct7_5 = 0; #10;
        // R-type: SUB (funct3 = 000, funct7[5] = 1)
        ALUOp = 2'b10; funct3 = 3'b000; funct7_5 = 1; #10;
        // R-type: AND (funct3 = 111)
        ALUOp = 2'b10; funct3 = 3'b111; funct7_5 = 0; #10;
        // R-type: SRL (funct3 = 101, funct7[5] = 0)
        ALUOp = 2'b10; funct3 = 3'b101; funct7_5 = 0; #10;
        // R-type: SRA (funct3 = 101, funct7[5] = 1)
        ALUOp = 2'b10; funct3 = 3'b101; funct7_5 = 1; #10;

        // I-type: ADDI
        ALUOp = 2'b11; funct3 = 3'b000; funct7_5 = 0; #10;
        // I-type: SLTIU
        ALUOp = 2'b11; funct3 = 3'b011; funct7_5 = 0; #10;
        // I-type: SRLI
        ALUOp = 2'b11; funct3 = 3'b101; funct7_5 = 0; #10;
        // I-type: SRAI
        ALUOp = 2'b11; funct3 = 3'b101; funct7_5 = 1; #10;

        // Load/Store: ADD (ALUOp = 00)
        ALUOp = 2'b00; funct3 = 3'b000; funct7_5 = 0; #10;
        // Branch: SUB (ALUOp = 01)
        ALUOp = 2'b01; funct3 = 3'b000; funct7_5 = 0; #10;

        $finish;
    end

endmodule

sim/alu_control.vcd
$date
	Wed May 28 00:59:59 2025
$end
$version
	Icarus Verilog
$end
$timescale
	1ps
$end
$scope module alu_control_tb $end
$var wire 4 ! alu_control [3:0] $end
$var reg 2 " ALUOp [1:0] $end
$var reg 3 # funct3 [2:0] $end
$var reg 1 $ funct7_5 $end
$scope module uut $end
$var wire 2 % ALUOp [1:0] $end
$var wire 3 & funct3 [2:0] $end
$var wire 1 $ funct7_5 $end
$var reg 4 ' alu_control [3:0] $end
$upscope $end
$upscope $end
$enddefinitions $end
$comment Show the parameter values. $end
$dumpall
$end
#0
$dumpvars
b10 '
b0 &
b10 %
0$
b0 #
b10 "
b10 !
$end
#10000
b110 !
b110 '
1$
#20000
b0 !
b0 '
0$
b111 #
b111 &
#30000
b101 !
b101 '
b101 #
b101 &
#40000
b1101 !
b1101 '
1$
#50000
b10 !
b10 '
0$
b0 #
b0 &
b11 "
b11 %
#60000
b1000 !
b1000 '
b11 #
b11 &
#70000
b101 !
b101 '
b101 #
b101 &
#80000
b1101 !
b1101 '
1$
#90000
b10 !
b10 '
0$
b0 #
b0 &
b0 "
b0 %
#100000
b110 !
b110 '
b1 "
b1 %
