src/alu.v
module alu (
    input wire [31:0] a, b,
    input wire [3:0] alu_control,
    output reg [31:0] result,
    output wire zero
);

    assign zero = (result == 0);

    always @(*) begin
        case (alu_control)
            4'b0000: result = a & b;                     // AND
            4'b0001: result = a | b;                     // OR
            4'b0010: result = a + b;                     // ADD
            4'b0110: result = a - b;                     // SUB
            4'b0011: result = a ^ b;                     // XOR
            4'b0100: result = a << b[4:0];               // SLL
            4'b0101: result = a >> b[4:0];               // SRL
            4'b1101: result = $signed(a) >>> b[4:0];     // SRA
            4'b0111: result = ($signed(a) < $signed(b)) ? 1 : 0; // SLT
            4'b1000: result = (a < b) ? 1 : 0;           // SLTU
            default: result = 0;
        endcase
    end
endmodule

src/imm_gen.v
module imm_gen (
    input wire [31:0] instr,
    output reg [31:0] imm_out
);
    always @(*) begin
        case (instr[6:0])
            7'b0010011, // I-type ALU
            7'b0000011, // Loads
            7'b1100111: // JALR
                imm_out = {{20{instr[31]}}, instr[31:20]};
            7'b0100011: // S-type stores
                imm_out = {{20{instr[31]}}, instr[31:25], instr[11:7]};
            7'b1100011: // B-type branches
                imm_out = {{19{instr[31]}}, instr[31], instr[7], instr[30:25], instr[11:8], 1'b0};
            7'b0110111, // LUI
            7'b0010111: // AUIPC
                imm_out = {instr[31:12], 12'b0};
            7'b1101111: // J-type JAL
                imm_out = {{11{instr[31]}}, instr[31], instr[19:12], instr[20], instr[30:21], 1'b0};
            default:
                imm_out = 32'b0;
        endcase
    end
endmodule

src/alu_control.v
module alu_control (
    input wire [1:0] ALUOp,
    input wire [2:0] funct3,
    input wire funct7_5, // bit 30 from funct7
    output reg [3:0] alu_control
);
    always @(*) begin
        case (ALUOp)
            2'b00: alu_control = 4'b0010;  // lw, sw → ADD
            2'b01: alu_control = 4'b0110;  // branch → SUB
            2'b10: begin  // R-type
                case ({funct7_5, funct3})
                    4'b0000: alu_control = 4'b0010; // ADD
                    4'b1000: alu_control = 4'b0110; // SUB
                    4'b0001: alu_control = 4'b0100; // SLL
                    4'b0010: alu_control = 4'b0111; // SLT
                    4'b0011: alu_control = 4'b1000; // SLTU
                    4'b0100: alu_control = 4'b0011; // XOR
                    4'b0101: alu_control = 4'b0101; // SRL
                    4'b1101: alu_control = 4'b1101; // SRA
                    4'b0110: alu_control = 4'b0001; // OR
                    4'b0111: alu_control = 4'b0000; // AND
                    default: alu_control = 4'b1111; // INVALID
                endcase
            end
            2'b11: begin  // I-type ALU ops
                case (funct3)
                    3'b000: alu_control = 4'b0010; // ADDI
                    3'b010: alu_control = 4'b0111; // SLTI
                    3'b011: alu_control = 4'b1000; // SLTIU
                    3'b100: alu_control = 4'b0011; // XORI
                    3'b110: alu_control = 4'b0001; // ORI
                    3'b111: alu_control = 4'b0000; // ANDI
                    3'b001: alu_control = 4'b0100; // SLLI
                    3'b101: alu_control = (funct7_5) ? 4'b1101 : 4'b0101; // SRAI / SRLI
                    default: alu_control = 4'b1111;
                endcase
            end
            default: alu_control = 4'b1111;
        endcase
    end
endmodule

src/regfile.v
module regfile (
    input wire clk,
    input wire we,                         // Write enable
    input wire [4:0] rs1, rs2, rd,         // Register addresses
    input wire [31:0] wd,                  // Write data
    output wire [31:0] rd1, rd2            // Read data outputs
);
    reg [31:0] regs [0:31];

    // Read (asynchronous)
    assign rd1 = (rs1 == 0) ? 0 : regs[rs1];
    assign rd2 = (rs2 == 0) ? 0 : regs[rs2];

    // Write (synchronous)
    always @(posedge clk) begin
        if (we && (rd != 0)) begin
            regs[rd] <= wd;
        end
    end
endmodule

src/execute.v
module execute (
    input wire clk,
    input wire we,                     // Write enable for register file
    input wire [1:0] alu_op,          // ALUOp from control unit
    input wire [4:0] rs1, rs2, rd,    // Register addresses
    input wire [31:0] instr,          // Full instruction for immediate generation
    input wire alu_src,               // Select between register or immediate
    input wire [2:0] funct3,
    input wire funct7_5,
    output wire [31:0] alu_result,
    output wire zero,
    output wire [31:0] rd1, rd2
);

    wire [31:0] op2;
    wire [3:0] alu_control;
    wire [31:0] imm;

    // Register file
    regfile rf (
        .clk(clk),
        .we(we),
        .rs1(rs1),
        .rs2(rs2),
        .rd(rd),
        .wd(alu_result),
        .rd1(rd1),
        .rd2(rd2)
    );

    // ALU control
    alu_control alu_ctl (
        .ALUOp(alu_op),
        .funct3(funct3),
        .funct7_5(funct7_5),
        .alu_control(alu_control)
    );

    // Immediate generator
    imm_gen imm_generator (
        .instr(instr),
        .imm_out(imm)
    );

    // ALU second operand selection
    assign op2 = (alu_src) ? imm : rd2;

    // ALU
    alu alu_core (
        .a(rd1),
        .b(op2),
        .alu_control(alu_control),
        .result(alu_result),
        .zero(zero)
    );

endmodule

base_cpu/src/control_unit.v
module control_unit(
    input  wire [6:0] opcode,
    input  wire [2:0] funct3,
    input  wire [6:0] funct7,
    output reg  [1:0] ALUOp,
    output reg  RegWrite,
    output reg  MemRead,
    output reg  MemWrite,
    output reg  Branch,
    output reg  Jump,
    output reg  ALUSrc
);

    always @(*) begin
        // Default values
        ALUOp    = 2'b00;
        RegWrite = 0;
        MemRead  = 0;
        MemWrite = 0;
        Branch   = 0;
        Jump     = 0;
        ALUSrc   = 0;

        case (opcode)
            7'b0110011: begin // R-type
                RegWrite = 1;
                ALUOp    = 2'b10;
                ALUSrc   = 0;
            end
            7'b0010011: begin // I-type ALU
                RegWrite = 1;
                ALUOp    = 2'b11;
                ALUSrc   = 1;
            end
            7'b0000011: begin // Load
                RegWrite = 1;
                MemRead  = 1;
                ALUOp    = 2'b00;
                ALUSrc   = 1;
            end
            7'b0100011: begin // Store
                MemWrite = 1;
                ALUOp    = 2'b00;
                ALUSrc   = 1;
            end
            7'b1100011: begin // Branch
                Branch   = 1;
                ALUOp    = 2'b01;
                ALUSrc   = 0;
            end
            7'b1101111: begin // JAL
                Jump     = 1;
                RegWrite = 1;
            end
            7'b1100111: begin // JALR
                Jump     = 1;
                RegWrite = 1;
                ALUSrc   = 1;
                ALUOp    = 2'b00;
            end
            default: begin
            end
        endcase
    end
endmodule

src/instr_mem.v
module instr_mem #(
    parameter INIT_FILE = "program.mem"
) (
    input wire [31:0] addr,
    output wire [31:0] instr
);
    reg [31:0] mem [0:255];  // 1KB instruction memory (256 words)

    initial begin
        $readmemh(INIT_FILE, mem);  // Load instructions from hex file
    end

    assign instr = mem[addr[9:2]];  // Word-aligned address (ignore bottom 2 bits)
endmodule

accel_cpu/src/pc.v
module pc(
    input wire clk,
    input wire reset,
    input wire [31:0] next_pc,
    output reg [31:0] pc_out
);
    always @(posedge clk or posedge reset) begin
        if (reset)
            pc_out <= 32'h00000000;
        else
            pc_out <= next_pc;
    end
endmodule

src/cpu_fetch.v
module cpu_fetch (
    input  wire        clk,
    input  wire        reset,

    // Control signals / targets
    input  wire        jal,            // jal instruction
    input  wire        jalr,           // jalr instruction
    input  wire        branch,         // conditional branch instruction
    input  wire        branch_taken,   // result of branch comparison from ALU
    input  wire [31:0] branch_target,  // PC-relative target for jal/branch
    input  wire [31:0] jalr_target,    // Target address for jalr

    output wire [31:0] instr,
    output wire [31:0] pc_out
);
    wire [31:0] next_pc;

    // Program Counter instance
    pc pc_inst (
        .clk(clk),
        .reset(reset),
        .next_pc(next_pc),
        .pc_out(pc_out)
    );

    // Instruction Memory instance
    instr_mem imem (
        .addr(pc_out),
        .instr(instr)
    );

    // Next PC generation with branch/jump handling
    wire [31:0] pc_plus4 = pc_out + 4;

    assign next_pc = jal  ? branch_target :
                     jalr ? jalr_target  :
                     (branch && branch_taken) ? branch_target :
                     pc_plus4;

endmodule

src/cpu.v
module cpu(
    input wire clk,
    input wire reset
);
    wire [31:0] instr;
    wire [31:0] pc_out;

    cpu_fetch fetch_unit(
        .clk(clk),
        .reset(reset),
        .jal(1'b0),
        .jalr(1'b0),
        .branch(1'b0),
        .branch_taken(1'b0),
        .branch_target(32'b0),
        .jalr_target(32'b0),
        .instr(instr),
        .pc_out(pc_out)
    );

    // Decode fields
    wire [6:0] opcode = instr[6:0];
    wire [2:0] funct3 = instr[14:12];
    wire [6:0] funct7 = instr[31:25];
    wire [4:0] rd  = instr[11:7];
    wire [4:0] rs1 = instr[19:15];
    wire [4:0] rs2 = instr[24:20];

    // Immediate (I-type for now)
    wire [31:0] imm_i = {{20{instr[31]}}, instr[31:20]};

    // Control signals
    wire [1:0] ALUOp;
    wire RegWrite, MemRead, MemWrite, Branch, Jump, ALUSrc;

    control_unit cu(
        .opcode(opcode),
        .funct3(funct3),
        .funct7(funct7),
        .ALUOp(ALUOp),
        .RegWrite(RegWrite),
        .MemRead(MemRead),
        .MemWrite(MemWrite),
        .Branch(Branch),
        .Jump(Jump),
        .ALUSrc(ALUSrc)
    );

    wire [31:0] alu_result;
    wire zero;

    execute exec_unit(
        .clk(clk),
        .we(RegWrite),
        .alu_op(ALUOp),
        .rs1(rs1),
        .rs2(rs2),
        .rd(rd),
        .instr(instr),
        .alu_src(ALUSrc),
        .funct3(funct3),
        .funct7_5(funct7[5]),
        .alu_result(alu_result),
        .zero(zero),
        .rd1(),
        .rd2()
    );

    // TODO: branch/jump/memory not implemented yet
endmodule

testbench/cpu_integration_tb.v
`timescale 1ns / 1ps

module cpu_integration_tb;
    reg clk, reset;
    integer test_count, pass_count, fail_count;

    // Instantiate the CPU
    cpu uut (
        .clk(clk),
        .reset(reset)
    );

    // Clock generation
    initial begin
        clk = 0;
        forever #5 clk = ~clk;
    end

    // Test sequence
    initial begin
        $dumpfile("sim/cpu_integration.vcd");
        $dumpvars(0, cpu_integration_tb);
        
        test_count = 0;
        pass_count = 0;
        fail_count = 0;
        
        $display("=== RISC-V CPU Integration Test ===");
        $display("Testing complete CPU with program.mem");
        
        // Reset phase
        reset = 1;
        $display("Phase 1: Reset (PC should be 0x00000000)");
        @(posedge clk);
        @(posedge clk);
        
        // Check initial state
        test_count = test_count + 1;
        if (uut.pc_out == 32'h00000000) begin
            $display("✓ PASS: PC reset to 0x00000000");
            pass_count = pass_count + 1;
        end else begin
            $display("✗ FAIL: PC = 0x%h, expected 0x00000000", uut.pc_out);
            fail_count = fail_count + 1;
        end
        
        // Start execution
        reset = 0;
        $display("\nPhase 2: Instruction Execution");
        
        // Wait for first instruction to be fetched
        @(posedge clk);
        $display("Instruction 1: 0x%h (NOP - addi x0, x0, 0)", uut.instr);
        
        // Execute first instruction (NOP)
        @(posedge clk);
        test_count = test_count + 1;
        if (uut.pc_out == 32'h00000004) begin
            $display("✓ PASS: PC incremented to 0x00000004");
            pass_count = pass_count + 1;
        end else begin
            $display("✗ FAIL: PC = 0x%h, expected 0x00000004", uut.pc_out);
            fail_count = fail_count + 1;
        end
        
        // Wait for second instruction
        @(posedge clk);
        $display("Instruction 2: 0x%h (addi x1, x0, 1)", uut.instr);
        
        // Execute second instruction (addi x1, x0, 1)
        @(posedge clk);
        test_count = test_count + 1;
        if (uut.pc_out == 32'h00000008) begin
            $display("✓ PASS: PC incremented to 0x00000008");
            pass_count = pass_count + 1;
        end else begin
            $display("✗ FAIL: PC = 0x%h, expected 0x00000008", uut.pc_out);
            fail_count = fail_count + 1;
        end
        
        // Check if x1 was written (need to wait for register write)
        @(posedge clk);
        test_count = test_count + 1;
        if (uut.exec_unit.rf.regs[1] == 32'd1) begin
            $display("✓ PASS: x1 = %d (expected 1)", uut.exec_unit.rf.regs[1]);
            pass_count = pass_count + 1;
        end else begin
            $display("✗ FAIL: x1 = %d, expected 1", uut.exec_unit.rf.regs[1]);
            fail_count = fail_count + 1;
        end
        
        // Wait for third instruction
        @(posedge clk);
        $display("Instruction 3: 0x%h (addi x2, x1, 2)", uut.instr);
        
        // Execute third instruction (addi x2, x1, 2)
        @(posedge clk);
        test_count = test_count + 1;
        if (uut.pc_out == 32'h0000000c) begin
            $display("✓ PASS: PC incremented to 0x0000000c");
            pass_count = pass_count + 1;
        end else begin
            $display("✗ FAIL: PC = 0x%h, expected 0x0000000c", uut.pc_out);
            fail_count = fail_count + 1;
        end
        
        // Check if x2 was written correctly
        @(posedge clk);
        test_count = test_count + 1;
        if (uut.exec_unit.rf.regs[2] == 32'd3) begin
            $display("✓ PASS: x2 = %d (expected 3)", uut.exec_unit.rf.regs[2]);
            pass_count = pass_count + 1;
        end else begin
            $display("✗ FAIL: x2 = %d, expected 3", uut.exec_unit.rf.regs[2]);
            fail_count = fail_count + 1;
        end
        
        // Wait for fourth instruction
        @(posedge clk);
        $display("Instruction 4: 0x%h (addi x3, x2, 3)", uut.instr);
        
        // Execute fourth instruction (addi x3, x2, 3)
        @(posedge clk);
        test_count = test_count + 1;
        if (uut.pc_out == 32'h00000010) begin
            $display("✓ PASS: PC incremented to 0x00000010");
            pass_count = pass_count + 1;
        end else begin
            $display("✗ FAIL: PC = 0x%h, expected 0x00000010", uut.pc_out);
            fail_count = fail_count + 1;
        end
        
        // Check if x3 was written correctly
        @(posedge clk);
        test_count = test_count + 1;
        if (uut.exec_unit.rf.regs[3] == 32'd6) begin
            $display("✓ PASS: x3 = %d (expected 6)", uut.exec_unit.rf.regs[3]);
            pass_count = pass_count + 1;
        end else begin
            $display("✗ FAIL: x3 = %d, expected 6", uut.exec_unit.rf.regs[3]);
            fail_count = fail_count + 1;
        end
        
        // Wait for fifth instruction (JAL)
        @(posedge clk);
        $display("Instruction 5: 0x%h (jal x0, 0 - infinite loop)", uut.instr);
        
        // Execute JAL instruction
        @(posedge clk);
        
        // Display final register state
        $display("\n=== Final Register State ===");
        $display("x0 = %d (should always be 0)", uut.exec_unit.rf.regs[0]);
        $display("x1 = %d (should be 1)", uut.exec_unit.rf.regs[1]);
        $display("x2 = %d (should be 3)", uut.exec_unit.rf.regs[2]);
        $display("x3 = %d (should be 6)", uut.exec_unit.rf.regs[3]);
        
        // Display control signals for last instruction
        $display("\n=== Control Signals (Last Instruction) ===");
        $display("ALUOp = %b", uut.ALUOp);
        $display("RegWrite = %b", uut.RegWrite);
        $display("ALUSrc = %b", uut.ALUSrc);
        $display("Branch = %b", uut.Branch);
        $display("Jump = %b", uut.Jump);
        
        // Display ALU results
        $display("\n=== ALU Results (Last Instruction) ===");
        $display("ALU Result = %d (0x%h)", uut.alu_result, uut.alu_result);
        $display("Zero Flag = %b", uut.zero);
        
        // Test summary
        $display("\n=== Test Summary ===");
        $display("Total Tests: %d", test_count);
        $display("Passed: %d", pass_count);
        $display("Failed: %d", fail_count);
        $display("Success Rate: %.1f%%", (pass_count * 100.0) / test_count);
        
        if (fail_count == 0) begin
            $display("🎉 ALL TESTS PASSED! CPU is working correctly.");
        end else begin
            $display("❌ Some tests failed. Check the implementation.");
        end
        
        $finish;
    end

endmodule

sim/cpu_integration.vcd
$date
	Mon Jun  9 16:10:30 2025
$end
$version
	Icarus Verilog
$end
$timescale
	1ps
$end
$scope module cpu_integration_tb $end
$var reg 1 ! clk $end
$var reg 1 " reset $end
$var integer 32 # fail_count [31:0] $end
$var integer 32 $ pass_count [31:0] $end
$var integer 32 % test_count [31:0] $end
$scope module uut $end
$var wire 1 ! clk $end
$var wire 1 " reset $end
$var wire 1 & zero $end
$var wire 5 ' rs2 [4:0] $end
$var wire 5 ( rs1 [4:0] $end
$var wire 5 ) rd [4:0] $end
$var wire 32 * pc_out [31:0] $end
$var wire 7 + opcode [6:0] $end
$var wire 32 , instr [31:0] $end
$var wire 32 - imm_i [31:0] $end
$var wire 7 . funct7 [6:0] $end
$var wire 3 / funct3 [2:0] $end
$var wire 32 0 alu_result [31:0] $end
$var wire 1 1 RegWrite $end
$var wire 1 2 MemWrite $end
$var wire 1 3 MemRead $end
$var wire 1 4 Jump $end
$var wire 1 5 Branch $end
$var wire 1 6 ALUSrc $end
$var wire 2 7 ALUOp [1:0] $end
$scope module cu $end
$var wire 3 8 funct3 [2:0] $end
$var wire 7 9 funct7 [6:0] $end
$var wire 7 : opcode [6:0] $end
$var reg 2 ; ALUOp [1:0] $end
$var reg 1 6 ALUSrc $end
$var reg 1 5 Branch $end
$var reg 1 4 Jump $end
$var reg 1 3 MemRead $end
$var reg 1 2 MemWrite $end
$var reg 1 1 RegWrite $end
$upscope $end
$scope module exec_unit $end
$var wire 2 < alu_op [1:0] $end
$var wire 1 6 alu_src $end
$var wire 1 ! clk $end
$var wire 3 = funct3 [2:0] $end
$var wire 1 > funct7_5 $end
$var wire 5 ? rd [4:0] $end
$var wire 5 @ rs1 [4:0] $end
$var wire 5 A rs2 [4:0] $end
$var wire 1 1 we $end
$var wire 1 & zero $end
$var wire 32 B rd2 [31:0] $end
$var wire 32 C rd1 [31:0] $end
$var wire 32 D op2 [31:0] $end
$var wire 32 E instr [31:0] $end
$var wire 32 F imm [31:0] $end
$var wire 32 G alu_result [31:0] $end
$var wire 4 H alu_control [3:0] $end
$scope module alu_core $end
$var wire 32 I b [31:0] $end
$var wire 1 & zero $end
$var wire 4 J alu_control [3:0] $end
$var wire 32 K a [31:0] $end
$var reg 32 L result [31:0] $end
$upscope $end
$scope module alu_ctl $end
$var wire 2 M ALUOp [1:0] $end
$var wire 3 N funct3 [2:0] $end
$var wire 1 > funct7_5 $end
$var reg 4 O alu_control [3:0] $end
$upscope $end
$scope module imm_generator $end
$var wire 32 P instr [31:0] $end
$var reg 32 Q imm_out [31:0] $end
$upscope $end
$scope module rf $end
$var wire 1 ! clk $end
$var wire 5 R rd [4:0] $end
$var wire 5 S rs1 [4:0] $end
$var wire 5 T rs2 [4:0] $end
$var wire 32 U wd [31:0] $end
$var wire 1 1 we $end
$var wire 32 V rd2 [31:0] $end
$var wire 32 W rd1 [31:0] $end
$upscope $end
$upscope $end
$scope module fetch_unit $end
$var wire 1 X branch $end
$var wire 1 Y branch_taken $end
$var wire 32 Z branch_target [31:0] $end
$var wire 1 ! clk $end
$var wire 1 [ jal $end
$var wire 1 \ jalr $end
$var wire 32 ] jalr_target [31:0] $end
$var wire 32 ^ next_pc [31:0] $end
$var wire 1 " reset $end
$var wire 32 _ pc_plus4 [31:0] $end
$var wire 32 ` pc_out [31:0] $end
$var wire 32 a instr [31:0] $end
$scope module imem $end
$var wire 32 b instr [31:0] $end
$var wire 32 c addr [31:0] $end
$upscope $end
$scope module pc_inst $end
$var wire 1 ! clk $end
$var wire 32 d next_pc [31:0] $end
$var wire 1 " reset $end
$var reg 32 e pc_out [31:0] $end
$upscope $end
$upscope $end
$upscope $end
$upscope $end
$enddefinitions $end
$comment Show the parameter values. $end
$dumpall
$end
#0
$dumpvars
b0 e
b100 d
b0 c
b10011 b
b10011 a
b0 `
b100 _
b100 ^
b0 ]
0\
0[
b0 Z
0Y
0X
b0 W
b0 V
b0 U
b0 T
b0 S
b0 R
b0 Q
b10011 P
b10 O
b0 N
b11 M
b0 L
b0 K
b10 J
b0 I
b10 H
b0 G
b0 F
b10011 E
b0 D
b0 C
b0 B
b0 A
b0 @
b0 ?
0>
b0 =
b11 <
b11 ;
b10011 :
b0 9
b0 8
b11 7
16
05
04
03
02
11
b0 0
b0 /
b0 .
b0 -
b10011 ,
b10011 +
b0 *
b0 )
b0 (
b0 '
1&
b0 %
b0 $
b0 #
1"
0!
$end
#5000
1!
#10000
0!
#15000
0"
b1 $
b1 %
1!
#20000
0!
#25000
0&
b1 0
b1 G
b1 L
b1 U
bx B
bx V
b1 D
b1 I
b1 -
b1 '
b1 A
b1 T
b1 )
b1 ?
b1 R
b1 F
b1 Q
b100000000000010010011 ,
b100000000000010010011 E
b100000000000010010011 P
b100000000000010010011 a
b100000000000010010011 b
b1000 ^
b1000 d
b1000 _
b100 *
b100 `
b100 c
b100 e
1!
#30000
0!
#35000
b11 0
b11 G
b11 L
b11 U
b1 C
b1 K
b1 W
b10 D
b10 I
b10 -
b10 '
b10 A
b10 T
b1 (
b1 @
b1 S
b10 )
b10 ?
b10 R
b10 F
b10 Q
bx B
bx V
b1000001000000100010011 ,
b1000001000000100010011 E
b1000001000000100010011 P
b1000001000000100010011 a
b1000001000000100010011 b
b1100 ^
b1100 d
b1100 _
b1000 *
b1000 `
b1000 c
b1000 e
b10 $
b10 %
1!
#40000
0!
#45000
b110 0
b110 G
b110 L
b110 U
b11 C
b11 K
b11 W
b11 D
b11 I
b11 -
b11 '
b11 A
b11 T
b10 (
b10 @
b10 S
b11 )
b11 ?
b11 R
b11 F
b11 Q
bx B
bx V
b1100010000000110010011 ,
b1100010000000110010011 E
b1100010000000110010011 P
b1100010000000110010011 a
b1100010000000110010011 b
b10000 ^
b10000 d
b10000 _
b1100 *
b1100 `
b1100 c
b1100 e
1!
#50000
0!
#55000
1&
b0 0
b0 G
b0 L
b0 U
b0 C
b0 K
b0 W
14
06
11
b0 7
b0 ;
b0 <
b0 M
b0 D
b0 I
b0 -
b0 '
b0 A
b0 T
b0 (
b0 @
b0 S
b0 )
b0 ?
b0 R
b1101111 +
b1101111 :
b0 F
b0 Q
b0 B
b0 V
b1101111 ,
b1101111 E
b1101111 P
b1101111 a
b1101111 b
b10100 ^
b10100 d
b10100 _
b10000 *
b10000 `
b10000 c
b10000 e
b1 #
b11 %
1!
#60000
0!
#65000
bx D
bx I
x&
bx 0
bx G
bx L
bx U
bx B
bx V
bx C
bx K
bx W
x>
04
01
bx -
bx '
bx A
bx T
bx (
bx @
bx S
bx )
bx ?
bx R
bx .
bx 9
bx /
bx 8
bx =
bx N
bx +
bx :
bx ,
bx E
bx P
bx a
bx b
b11000 ^
b11000 d
b11000 _
b10100 *
b10100 `
b10100 c
b10100 e
b11 $
b100 %
1!
#70000
0!
#75000
b11100 ^
b11100 d
b11100 _
b11000 *
b11000 `
b11000 c
b11000 e
1!
#80000
0!
#85000
b100000 ^
b100000 d
b100000 _
b11100 *
b11100 `
b11100 c
b11100 e
b10 #
b101 %
1!
#90000
0!
#95000
b100100 ^
b100100 d
b100100 _
b100000 *
b100000 `
b100000 c
b100000 e
b100 $
b110 %
1!
#100000
0!
#105000
b101000 ^
b101000 d
b101000 _
b100100 *
b100100 `
b100100 c
b100100 e
1!
#110000
0!
#115000
b101100 ^
b101100 d
b101100 _
b101000 *
b101000 `
b101000 c
b101000 e
b11 #
b111 %
1!
#120000
0!
#125000
b110000 ^
b110000 d
b110000 _
b101100 *
b101100 `
b101100 c
b101100 e
b101 $
b1000 %
1!
#130000
0!
#135000
b110100 ^
b110100 d
b110100 _
b110000 *
b110000 `
b110000 c
b110000 e
1!
#140000
0!
#145000
b111000 ^
b111000 d
b111000 _
b110100 *
b110100 `
b110100 c
b110100 e
1!
