src/instr_mem.v
module instr_mem (
    input wire [31:0] addr,
    output wire [31:0] instr
);
    reg [31:0] mem [0:255];  // 1KB instruction memory (256 words)

    initial begin
        $readmemh("program.mem", mem);  // Load instructions from hex file
    end

    assign instr = mem[addr[9:2]];  // Word-aligned address (ignore bottom 2 bits)
endmodule

accel_cpu/src/pc.v
module pc(
    input wire clk,
    input wire reset,
    input wire [31:0] next_pc,
    output reg [31:0] pc_out
);
    always @(posedge clk or posedge reset) begin
        if (reset)
            pc_out <= 32'h00000000;
        else
            pc_out <= next_pc;
    end
endmodule

src/cpu_fetch.v
module cpu_fetch (
    input wire clk,
    input wire reset,
    output wire [31:0] instr,
    output wire [31:0] pc_out
);
    wire [31:0] next_pc;

    // Program Counter instance
    pc pc_inst (
        .clk(clk),
        .reset(reset),
        .next_pc(next_pc),
        .pc_out(pc_out)
    );

    // Instruction Memory instance
    instr_mem imem (
        .addr(pc_out),
        .instr(instr)
    );

    // PC always increments by 4 (for now, no branches)
    assign next_pc = pc_out + 4;

endmodule

testbench/cpu_fetch_tb.v
`timescale 1ns / 1ps

module cpu_fetch_tb;

    reg clk, reset;
    wire [31:0] instr, pc_out;

    cpu_fetch uut (
        .clk(clk),
        .reset(reset),
        .instr(instr),
        .pc_out(pc_out)
    );

    initial begin
        $dumpfile("sim/fetch.vcd");
        $dumpvars(0, cpu_fetch_tb);

        clk = 0; reset = 1;
        #10 reset = 0;
        #100 $finish;
    end

    always #5 clk = ~clk;

endmodule

sim/fetch.vcd
$date
	Wed May 28 00:36:02 2025
$end
$version
	Icarus Verilog
$end
$timescale
	1ps
$end
$scope module cpu_fetch_tb $end
$var wire 32 ! pc_out [31:0] $end
$var wire 32 " instr [31:0] $end
$var reg 1 # clk $end
$var reg 1 $ reset $end
$scope module uut $end
$var wire 1 # clk $end
$var wire 1 $ reset $end
$var wire 32 % pc_out [31:0] $end
$var wire 32 & next_pc [31:0] $end
$var wire 32 ' instr [31:0] $end
$scope module imem $end
$var wire 32 ( instr [31:0] $end
$var wire 32 ) addr [31:0] $end
$upscope $end
$scope module pc_inst $end
$var wire 1 # clk $end
$var wire 32 * next_pc [31:0] $end
$var wire 1 $ reset $end
$var reg 32 + pc_out [31:0] $end
$upscope $end
$upscope $end
$upscope $end
$enddefinitions $end
$comment Show the parameter values. $end
$dumpall
$end
#0
$dumpvars
b0 +
b100 *
b0 )
b10011 (
b10011 '
b100 &
b0 %
1$
0#
b10011 "
b0 !
$end
#5000
1#
#10000
0#
0$
#15000
b100000000000010010011 "
b100000000000010010011 '
b100000000000010010011 (
b1000 &
b1000 *
b100 !
b100 %
b100 )
b100 +
1#
#20000
0#
#25000
b1000001000000100010011 "
b1000001000000100010011 '
b1000001000000100010011 (
b1100 &
b1100 *
b1000 !
b1000 %
b1000 )
b1000 +
1#
#30000
0#
#35000
b1100010000000110010011 "
b1100010000000110010011 '
b1100010000000110010011 (
b10000 &
b10000 *
b1100 !
b1100 %
b1100 )
b1100 +
1#
#40000
0#
#45000
b1101111 "
b1101111 '
b1101111 (
b10100 &
b10100 *
b10000 !
b10000 %
b10000 )
b10000 +
1#
#50000
0#
#55000
bx "
bx '
bx (
b11000 &
b11000 *
b10100 !
b10100 %
b10100 )
b10100 +
1#
#60000
0#
#65000
b11100 &
b11100 *
b11000 !
b11000 %
b11000 )
b11000 +
1#
#70000
0#
#75000
b100000 &
b100000 *
b11100 !
b11100 %
b11100 )
b11100 +
1#
#80000
0#
#85000
b100100 &
b100100 *
b100000 !
b100000 %
b100000 )
b100000 +
1#
#90000
0#
#95000
b101000 &
b101000 *
b100100 !
b100100 %
b100100 )
b100100 +
1#
#100000
0#
#105000
b101100 &
b101100 *
b101000 !
b101000 %
b101000 )
b101000 +
1#
