accel_cpu/src/alu.v
module alu (
    input wire [31:0] a, b,
    input wire [3:0] alu_control,
    input wire alu_ctrl_relu,
    input wire alu_ctrl_matmul,
    input wire alu_ctrl_dotprod,
    output reg [31:0] result,
    output wire zero
);

    assign zero = (result == 0);

    // ReLU
    wire [31:0] relu_out = (a[31] == 1'b1) ? 32'd0 : a;

    // Packed 16-bit operands
    wire [15:0] aa = a[15:0];
    wire [15:0] bb = a[31:16];
    wire [15:0] cc = b[15:0];
    wire [15:0] dd = b[31:16];
    wire [31:0] dot_out    = $signed(aa)*$signed(cc) + $signed(bb)*$signed(dd);
    wire [31:0] matmul_out = dot_out;

    always @(*) begin
        case (1'b1)
            alu_ctrl_relu:    result = relu_out;
            alu_ctrl_matmul:  result = matmul_out;
            alu_ctrl_dotprod: result = dot_out;
            default: begin
                case (alu_control)
                    4'b0000: result = a & b;                     // AND
                    4'b0001: result = a | b;                     // OR
                    4'b0010: result = a + b;                     // ADD
                    4'b0110: result = a - b;                     // SUB
                    4'b0011: result = a ^ b;                     // XOR
                    4'b0100: result = a << b[4:0];               // SLL
                    4'b0101: result = a >> b[4:0];               // SRL
                    4'b1101: result = $signed(a) >>> b[4:0];     // SRA
                    4'b0111: result = ($signed(a) < $signed(b)) ? 1 : 0; // SLT
                    4'b1000: result = (a < b) ? 1 : 0;           // SLTU
                    4'b1001: result = a * b;                     // MUL
                    default: result = 0;
                endcase
            end
        endcase
    end
endmodule

src/imm_gen.v
module imm_gen (
    input wire [31:0] instr,
    output reg [31:0] imm_out
);
    always @(*) begin
        case (instr[6:0])
            7'b0010011, // I-type ALU
            7'b0000011, // Loads
            7'b1100111: // JALR
                imm_out = {{20{instr[31]}}, instr[31:20]};
            7'b0100011: // S-type stores
                imm_out = {{20{instr[31]}}, instr[31:25], instr[11:7]};
            7'b1100011: // B-type branches
                imm_out = {{19{instr[31]}}, instr[31], instr[7], instr[30:25], instr[11:8], 1'b0};
            7'b0110111, // LUI
            7'b0010111: // AUIPC
                imm_out = {instr[31:12], 12'b0};
            7'b1101111: // J-type JAL
                imm_out = {{11{instr[31]}}, instr[31], instr[19:12], instr[20], instr[30:21], 1'b0};
            default:
                imm_out = 32'b0;
        endcase
    end
endmodule

accel_cpu/src/alu_control.v
module alu_control (
    input wire [1:0] ALUOp,
    input wire [2:0] funct3,
    input wire [6:0] funct7,
    output reg [3:0] alu_control
);
    always @(*) begin
        case (ALUOp)
            2'b00: alu_control = 4'b0010;  // lw, sw → ADD
            2'b01: alu_control = 4'b0110;  // branch → SUB
            2'b10: begin  // R-type
                case ({funct7, funct3})
                    10'b0000000_000: alu_control = 4'b0010; // ADD
                    10'b0100000_000: alu_control = 4'b0110; // SUB
                    10'b0000000_001: alu_control = 4'b0100; // SLL
                    10'b0000000_010: alu_control = 4'b0111; // SLT
                    10'b0000000_011: alu_control = 4'b1000; // SLTU
                    10'b0000000_100: alu_control = 4'b0011; // XOR
                    10'b0000000_101: alu_control = 4'b0101; // SRL
                    10'b0100000_101: alu_control = 4'b1101; // SRA
                    10'b0000000_110: alu_control = 4'b0001; // OR
                    10'b0000000_111: alu_control = 4'b0000; // AND
                    10'b0000001_000: alu_control = 4'b1001; // MUL
                    default: alu_control = 4'b1111; // INVALID
                endcase
            end
            2'b11: begin  // I-type ALU ops
                case (funct3)
                    3'b000: alu_control = 4'b0010; // ADDI
                    3'b010: alu_control = 4'b0111; // SLTI
                    3'b011: alu_control = 4'b1000; // SLTIU
                    3'b100: alu_control = 4'b0011; // XORI
                    3'b110: alu_control = 4'b0001; // ORI
                    3'b111: alu_control = 4'b0000; // ANDI
                    3'b001: alu_control = 4'b0100; // SLLI
                    3'b101: alu_control = (funct7[5]) ? 4'b1101 : 4'b0101; // SRAI / SRLI
                    default: alu_control = 4'b1111;
                endcase
            end
            default: alu_control = 4'b1111;
        endcase
    end
endmodule

src/regfile.v
module regfile (
    input wire clk,
    input wire reset,
    input wire we,                         // Write enable
    input wire [4:0] rs1, rs2, rd,         // Register addresses
    input wire [31:0] wd,                  // Write data
    output wire [31:0] rd1, rd2            // Read data outputs
);
    reg [31:0] regs [0:31];

    // Read (asynchronous)
    assign rd1 = (rs1 == 0) ? 0 : regs[rs1];
    assign rd2 = (rs2 == 0) ? 0 : regs[rs2];

    // Write with synchronous reset
    integer i;
    always @(posedge clk) begin
        if (reset) begin
            for (i = 0; i < 32; i = i + 1)
                regs[i] <= 0;
        end else if (we && (rd != 0)) begin
            regs[rd] <= wd;
        end
    end
endmodule

accel_cpu/src/execute.v
module execute (
    input wire clk,
    input wire reset,
    input wire we,                     // Write enable for register file
    input wire [1:0] alu_op,          // ALUOp from control unit
    input wire [4:0] rs1, rs2, rd,    // Register addresses
    input wire [31:0] instr,          // Full instruction for immediate generation
    input wire alu_src,               // Select between register or immediate
    input wire [2:0] funct3,
    input wire [6:0] funct7,
    input wire alu_ctrl_relu,
    input wire alu_ctrl_matmul,
    input wire alu_ctrl_dotprod,
    input wire [31:0] wb_data,        // Data to write back to register file
    output wire [31:0] alu_result,
    output wire zero,
    output wire [31:0] rd1, rd2
);

    wire [31:0] op2;
    wire [3:0] alu_control;
    wire [31:0] imm;

    // Register file
    regfile rf (
        .clk(clk),
        .reset(reset),
        .we(we),
        .rs1(rs1),
        .rs2(rs2),
        .rd(rd),
        .wd(wb_data),
        .rd1(rd1),
        .rd2(rd2)
    );

    // ALU control
    alu_control alu_ctl (
        .ALUOp(alu_op),
        .funct3(funct3),
        .funct7(funct7),
        .alu_control(alu_control)
    );

    // Immediate generator
    imm_gen imm_generator (
        .instr(instr),
        .imm_out(imm)
    );

    // ALU second operand selection
    assign op2 = (alu_src) ? imm : rd2;

    // ALU
    alu alu_core (
        .a(rd1),
        .b(op2),
        .alu_control(alu_control),
        .alu_ctrl_relu(alu_ctrl_relu),
        .alu_ctrl_matmul(alu_ctrl_matmul),
        .alu_ctrl_dotprod(alu_ctrl_dotprod),
        .result(alu_result),
        .zero(zero)
    );

endmodule

base_cpu/src/data_mem.v
module data_mem(
    input wire clk,
    input wire mem_read,
    input wire mem_write,
    input wire [31:0] addr,
    input wire [31:0] write_data,
    output wire [31:0] read_data
);
    reg [31:0] mem [0:255];

    initial begin
        // Optionally pre-load memory from file
    end

    always @(posedge clk) begin
        if (mem_write) begin
            mem[addr[9:2]] <= write_data;
        end
    end

    assign read_data = mem_read ? mem[addr[9:2]] : 32'b0;
endmodule

accel_cpu/src/control_unit.v
module control_unit(
    input  wire [6:0] opcode,
    input  wire [2:0] funct3,
    input  wire [6:0] funct7,
    output reg  [1:0] ALUOp,
    output reg  RegWrite,
    output reg  MemRead,
    output reg  MemWrite,
    output reg  Branch,
    output reg  Jump,
    output reg  ALUSrc,
    output wire alu_ctrl_relu,
    output wire alu_ctrl_matmul,
    output wire alu_ctrl_dotprod
);

    // Custom instruction detection
    wire is_custom0 = (opcode == 7'b0001011);
    assign alu_ctrl_relu    = is_custom0 && (funct3 == 3'b000);
    assign alu_ctrl_matmul  = is_custom0 && (funct3 == 3'b001);
    assign alu_ctrl_dotprod = is_custom0 && (funct3 == 3'b010);

    always @(*) begin
        // Default values
        ALUOp    = 2'b00;
        RegWrite = 0;
        MemRead  = 0;
        MemWrite = 0;
        Branch   = 0;
        Jump     = 0;
        ALUSrc   = 0;

        case (opcode)
            7'b0110011: begin // R-type
                RegWrite = 1;
                ALUOp    = 2'b10;
                ALUSrc   = 0;
            end
            7'b0010011: begin // I-type ALU
                RegWrite = 1;
                ALUOp    = 2'b11;
                ALUSrc   = 1;
            end
            7'b0000011: begin // Load
                RegWrite = 1;
                MemRead  = 1;
                ALUOp    = 2'b00;
                ALUSrc   = 1;
            end
            7'b0100011: begin // Store
                MemWrite = 1;
                ALUOp    = 2'b00;
                ALUSrc   = 1;
            end
            7'b1100011: begin // Branch
                Branch   = 1;
                ALUOp    = 2'b01;
                ALUSrc   = 0;
            end
            7'b1101111: begin // JAL
                Jump     = 1;
                RegWrite = 1;
            end
            7'b1100111: begin // JALR
                Jump     = 1;
                RegWrite = 1;
                ALUSrc   = 1;
                ALUOp    = 2'b00;
            end
            7'b0001011: begin // custom-0
                RegWrite = 1;
                ALUOp    = 2'b10;
            end
            default: begin
            end
        endcase
    end
endmodule

src/instr_mem.v
module instr_mem #(
    parameter INIT_FILE = "program.mem"
) (
    input wire [31:0] addr,
    output wire [31:0] instr
);
    reg [31:0] mem [0:255];  // 1KB instruction memory (256 words)

    initial begin
        $readmemh(INIT_FILE, mem);  // Load instructions from hex file
    end

    assign instr = mem[addr[9:2]];  // Word-aligned address (ignore bottom 2 bits)
endmodule

accel_cpu/src/pc.v
module pc(
    input wire clk,
    input wire reset,
    input wire [31:0] next_pc,
    output reg [31:0] pc_out
);
    always @(posedge clk or posedge reset) begin
        if (reset)
            pc_out <= 32'h00000000;
        else
            pc_out <= next_pc;
    end
endmodule

src/cpu_fetch.v
module cpu_fetch #(
    parameter MEMFILE = "program.mem"
) (
    input  wire        clk,
    input  wire        reset,

    // Control signals / targets
    input  wire        jal,            // jal instruction
    input  wire        jalr,           // jalr instruction
    input  wire        branch,         // conditional branch instruction
    input  wire        branch_taken,   // result of branch comparison from ALU
    input  wire [31:0] branch_target,  // PC-relative target for jal/branch
    input  wire [31:0] jalr_target,    // Target address for jalr

    output wire [31:0] instr,
    output wire [31:0] pc_out
);
    wire [31:0] next_pc;

    // Program Counter instance
    pc pc_inst (
        .clk(clk),
        .reset(reset),
        .next_pc(next_pc),
        .pc_out(pc_out)
    );

    // Instruction Memory instance
    instr_mem #(.INIT_FILE(MEMFILE)) imem (
        .addr(pc_out),
        .instr(instr)
    );

    // Next PC generation with branch/jump handling
    wire [31:0] pc_plus4 = pc_out + 4;

    assign next_pc = jal  ? branch_target :
                     jalr ? jalr_target  :
                     (branch && branch_taken) ? branch_target :
                     pc_plus4;

endmodule

accel_cpu/src/cpu.v
module cpu #(
    parameter MEMFILE = "program.mem"
) (
    input wire clk,
    input wire reset,
    output reg [31:0] cycle_count
);
    wire [31:0] instr;
    wire [31:0] pc_out;

    // Performance counters
    reg [31:0] instr_count;
    reg [31:0] mem_read_count;
    reg [31:0] mem_write_count;
    reg [31:0] rf_read_count;
    reg [31:0] rf_write_count;

    // Signals for fetch stage
    wire jal, jalr;
    wire branch_taken;
    wire [31:0] branch_target, jalr_target;

    cpu_fetch #(.MEMFILE(MEMFILE)) fetch_unit(
        .clk(clk),
        .reset(reset),
        .jal(jal),
        .jalr(jalr),
        .branch(Branch),
        .branch_taken(branch_taken),
        .branch_target(branch_target),
        .jalr_target(jalr_target),
        .instr(instr),
        .pc_out(pc_out)
    );

    // Decode fields
    wire [6:0] opcode = instr[6:0];
    wire [2:0] funct3 = instr[14:12];
    wire [6:0] funct7 = instr[31:25];

    // Halt detection (using the EBREAK instruction)
    wire halt = (instr == 32'h0010_0073);
    wire [4:0] rd  = instr[11:7];
    wire [4:0] rs1 = instr[19:15];
    wire [4:0] rs2 = instr[24:20];

    // Immediate generator
    wire [31:0] imm;
    imm_gen imm_unit(
        .instr(instr),
        .imm_out(imm)
    );

    // Control signals
    wire [1:0] ALUOp;
    wire RegWrite, MemRead, MemWrite, Branch, Jump, ALUSrc;
    wire alu_ctrl_relu, alu_ctrl_matmul, alu_ctrl_dotprod;

    control_unit cu(
        .opcode(opcode),
        .funct3(funct3),
        .funct7(funct7),
        .ALUOp(ALUOp),
        .RegWrite(RegWrite),
        .MemRead(MemRead),
        .MemWrite(MemWrite),
        .Branch(Branch),
        .Jump(Jump),
        .ALUSrc(ALUSrc),
        .alu_ctrl_relu(alu_ctrl_relu),
        .alu_ctrl_matmul(alu_ctrl_matmul),
        .alu_ctrl_dotprod(alu_ctrl_dotprod)
    );

    // Register and ALU outputs
    wire [31:0] alu_result;
    wire zero;
    wire [31:0] rd1, rd2;
    wire [31:0] write_back_data;

    // Data memory
    wire [31:0] mem_data;
    data_mem dmem(
        .clk(clk),
        .mem_read(MemRead),
        .mem_write(MemWrite),
        .addr(alu_result),
        .write_data(rd2),
        .read_data(mem_data)
    );


    execute exec_unit(
        .clk(clk),
        .reset(reset),
        .we(RegWrite),
        .alu_op(ALUOp),
        .rs1(rs1),
        .rs2(rs2),
        .rd(rd),
        .instr(instr),
        .alu_src(ALUSrc),
        .funct3(funct3),
        .funct7(funct7),
        .alu_ctrl_relu(alu_ctrl_relu),
        .alu_ctrl_matmul(alu_ctrl_matmul),
        .alu_ctrl_dotprod(alu_ctrl_dotprod),
        .wb_data(write_back_data),
        .alu_result(alu_result),
        .zero(zero),
        .rd1(rd1),
        .rd2(rd2)
    );

    // PC increment
    wire [31:0] pc_plus4 = pc_out + 4;

    // Branch and jump target calculations
    assign branch_target = pc_out + imm;
    assign jalr_target   = (rd1 + imm) & 32'hffff_fffe;

    // Branch comparison helpers
    wire eq      = (rd1 == rd2);
    wire slt     = ($signed(rd1) < $signed(rd2));
    wire sltu    = (rd1 < rd2);

    // Branch decision based on funct3
    reg branch_cond;
    always @(*) begin
        case (funct3)
            3'b000: branch_cond = eq;          // BEQ
            3'b001: branch_cond = !eq;         // BNE
            3'b100: branch_cond = slt;         // BLT
            3'b101: branch_cond = !slt;        // BGE
            3'b110: branch_cond = sltu;        // BLTU
            3'b111: branch_cond = !sltu;       // BGEU
            default: branch_cond = 1'b0;
        endcase
    end

    assign branch_taken = Branch && branch_cond;

    // Distinguish between JAL and JALR
    assign jal  = Jump && (opcode == 7'b1101111);
    assign jalr = Jump && (opcode == 7'b1100111);

    // Writeback mux: priority Jump -> Load -> ALU
    assign write_back_data = jal | jalr ? pc_plus4 :
                              MemRead    ? mem_data  :
                              alu_result;

    // Cycle counter and other performance metrics
    always @(posedge clk) begin
        if (reset) begin
            cycle_count     <= 0;
            instr_count     <= 0;
            mem_read_count  <= 0;
            mem_write_count <= 0;
            rf_read_count   <= 0;
            rf_write_count  <= 0;
        end else if (!halt) begin
            cycle_count <= cycle_count + 1;
            instr_count <= instr_count + 1;

            // Memory access counters
            if (MemRead)
                mem_read_count <= mem_read_count + 1;
            if (MemWrite)
                mem_write_count <= mem_write_count + 1;

            // Register file read counters
            if ((opcode != 7'b1101111) && (rs1 != 0))
                rf_read_count <= rf_read_count + 1;
            if ((opcode == 7'b0110011 || opcode == 7'b0100011 || opcode == 7'b1100011) && (rs2 != 0))
                rf_read_count <= rf_read_count + 1;

            // Register file write counter
            if (RegWrite && rd != 0)
                rf_write_count <= rf_write_count + 1;
        end
    end

    // TODO: Power estimation hooks can be added for FPGA implementation
endmodule

accel_cpu/testbench/cpu_accel_tb.v
`timescale 1ns / 1ps

module cpu_accel_tb;
    reg clk = 0;
    reg reset;
    wire [31:0] cycle_count;

    cpu #(.MEMFILE("program.mem")) uut (
        .clk(clk),
        .reset(reset),
        .cycle_count(cycle_count)
    );

    always #5 clk = ~clk;

    initial begin
        $dumpfile("sim/cpu_accel_tb.vcd");
        $dumpvars(0, cpu_accel_tb);
        $display("=== Accelerator Instruction Test ===");

        reset = 1;
        @(posedge clk); @(posedge clk); reset = 0;

        repeat(50) @(posedge clk); #1;
        $display("ReLU(-1) = %0d", uut.exec_unit.rf.regs[2]);
        $display("ReLU(+5) = %0d", uut.exec_unit.rf.regs[4]);
        $display("Dot product = %0d", uut.exec_unit.rf.regs[7]);
        $display("MatMul results: %0d %0d %0d %0d",
                 uut.exec_unit.rf.regs[12], uut.exec_unit.rf.regs[13],
                 uut.exec_unit.rf.regs[14], uut.exec_unit.rf.regs[15]);
        $display("Cycles: %0d", cycle_count);
        $finish;
    end
endmodule

accel_cpu/sim/cpu_accel_tb.vcd
$date
	Tue Jul  1 02:09:59 2025
$end
$version
	Icarus Verilog
$end
$timescale
	1ps
$end
$scope module cpu_accel_tb $end
$var wire 32 ! cycle_count [31:0] $end
$var reg 1 " clk $end
$var reg 1 # reset $end
$scope module uut $end
$var wire 1 $ branch_taken $end
$var wire 1 " clk $end
$var wire 1 % jal $end
$var wire 1 & jalr $end
$var wire 32 ' jalr_target [31:0] $end
$var wire 1 # reset $end
$var wire 1 ( zero $end
$var wire 32 ) write_back_data [31:0] $end
$var wire 1 * sltu $end
$var wire 1 + slt $end
$var wire 5 , rs2 [4:0] $end
$var wire 5 - rs1 [4:0] $end
$var wire 32 . rd2 [31:0] $end
$var wire 32 / rd1 [31:0] $end
$var wire 5 0 rd [4:0] $end
$var wire 32 1 pc_plus4 [31:0] $end
$var wire 32 2 pc_out [31:0] $end
$var wire 7 3 opcode [6:0] $end
$var wire 32 4 mem_data [31:0] $end
$var wire 32 5 instr [31:0] $end
$var wire 32 6 imm [31:0] $end
$var wire 1 7 halt $end
$var wire 7 8 funct7 [6:0] $end
$var wire 3 9 funct3 [2:0] $end
$var wire 1 : eq $end
$var wire 32 ; branch_target [31:0] $end
$var wire 32 < alu_result [31:0] $end
$var wire 1 = alu_ctrl_relu $end
$var wire 1 > alu_ctrl_matmul $end
$var wire 1 ? alu_ctrl_dotprod $end
$var wire 1 @ RegWrite $end
$var wire 1 A MemWrite $end
$var wire 1 B MemRead $end
$var wire 1 C Jump $end
$var wire 1 D Branch $end
$var wire 1 E ALUSrc $end
$var wire 2 F ALUOp [1:0] $end
$var parameter 88 G MEMFILE $end
$var reg 1 H branch_cond $end
$var reg 32 I cycle_count [31:0] $end
$var reg 32 J instr_count [31:0] $end
$var reg 32 K mem_read_count [31:0] $end
$var reg 32 L mem_write_count [31:0] $end
$var reg 32 M rf_read_count [31:0] $end
$var reg 32 N rf_write_count [31:0] $end
$scope module cu $end
$var wire 1 ? alu_ctrl_dotprod $end
$var wire 1 > alu_ctrl_matmul $end
$var wire 1 = alu_ctrl_relu $end
$var wire 3 O funct3 [2:0] $end
$var wire 7 P funct7 [6:0] $end
$var wire 7 Q opcode [6:0] $end
$var wire 1 R is_custom0 $end
$var reg 2 S ALUOp [1:0] $end
$var reg 1 E ALUSrc $end
$var reg 1 D Branch $end
$var reg 1 C Jump $end
$var reg 1 B MemRead $end
$var reg 1 A MemWrite $end
$var reg 1 @ RegWrite $end
$upscope $end
$scope module dmem $end
$var wire 1 " clk $end
$var wire 1 B mem_read $end
$var wire 1 A mem_write $end
$var wire 32 T write_data [31:0] $end
$var wire 32 U read_data [31:0] $end
$var wire 32 V addr [31:0] $end
$upscope $end
$scope module exec_unit $end
$var wire 1 ? alu_ctrl_dotprod $end
$var wire 1 > alu_ctrl_matmul $end
$var wire 1 = alu_ctrl_relu $end
$var wire 2 W alu_op [1:0] $end
$var wire 1 E alu_src $end
$var wire 1 " clk $end
$var wire 3 X funct3 [2:0] $end
$var wire 7 Y funct7 [6:0] $end
$var wire 5 Z rd [4:0] $end
$var wire 1 # reset $end
$var wire 5 [ rs1 [4:0] $end
$var wire 5 \ rs2 [4:0] $end
$var wire 32 ] wb_data [31:0] $end
$var wire 1 @ we $end
$var wire 1 ( zero $end
$var wire 32 ^ rd2 [31:0] $end
$var wire 32 _ rd1 [31:0] $end
$var wire 32 ` op2 [31:0] $end
$var wire 32 a instr [31:0] $end
$var wire 32 b imm [31:0] $end
$var wire 32 c alu_result [31:0] $end
$var wire 4 d alu_control [3:0] $end
$scope module alu_core $end
$var wire 1 ? alu_ctrl_dotprod $end
$var wire 1 > alu_ctrl_matmul $end
$var wire 1 = alu_ctrl_relu $end
$var wire 32 e b [31:0] $end
$var wire 32 f matmul_out [31:0] $end
$var wire 1 ( zero $end
$var wire 32 g relu_out [31:0] $end
$var wire 32 h dot_out [31:0] $end
$var wire 16 i dd [15:0] $end
$var wire 16 j cc [15:0] $end
$var wire 16 k bb [15:0] $end
$var wire 4 l alu_control [3:0] $end
$var wire 16 m aa [15:0] $end
$var wire 32 n a [31:0] $end
$var reg 32 o result [31:0] $end
$upscope $end
$scope module alu_ctl $end
$var wire 2 p ALUOp [1:0] $end
$var wire 3 q funct3 [2:0] $end
$var wire 7 r funct7 [6:0] $end
$var reg 4 s alu_control [3:0] $end
$upscope $end
$scope module imm_generator $end
$var wire 32 t instr [31:0] $end
$var reg 32 u imm_out [31:0] $end
$upscope $end
$scope module rf $end
$var wire 1 " clk $end
$var wire 5 v rd [4:0] $end
$var wire 1 # reset $end
$var wire 5 w rs1 [4:0] $end
$var wire 5 x rs2 [4:0] $end
$var wire 32 y wd [31:0] $end
$var wire 1 @ we $end
$var wire 32 z rd2 [31:0] $end
$var wire 32 { rd1 [31:0] $end
$var integer 32 | i [31:0] $end
$upscope $end
$upscope $end
$scope module fetch_unit $end
$var wire 1 D branch $end
$var wire 1 $ branch_taken $end
$var wire 32 } branch_target [31:0] $end
$var wire 1 " clk $end
$var wire 1 % jal $end
$var wire 1 & jalr $end
$var wire 32 ~ jalr_target [31:0] $end
$var wire 1 # reset $end
$var wire 32 !" pc_plus4 [31:0] $end
$var wire 32 "" pc_out [31:0] $end
$var wire 32 #" next_pc [31:0] $end
$var wire 32 $" instr [31:0] $end
$var parameter 88 %" MEMFILE $end
$scope module imem $end
$var wire 32 &" instr [31:0] $end
$var wire 32 '" addr [31:0] $end
$var parameter 88 (" INIT_FILE $end
$upscope $end
$scope module pc_inst $end
$var wire 1 " clk $end
$var wire 32 )" next_pc [31:0] $end
$var wire 1 # reset $end
$var reg 32 *" pc_out [31:0] $end
$upscope $end
$upscope $end
$scope module imm_unit $end
$var wire 32 +" instr [31:0] $end
$var reg 32 ," imm_out [31:0] $end
$upscope $end
$upscope $end
$upscope $end
$enddefinitions $end
$comment Show the parameter values. $end
$dumpall
b111000001110010011011110110011101110010011000010110110100101110011011010110010101101101 ("
b111000001110010011011110110011101110010011000010110110100101110011011010110010101101101 %"
b111000001110010011011110110011101110010011000010110110100101110011011010110010101101101 G
$end
#0
$dumpvars
b11111111111111111111111111111111 ,"
b11111111111100000000000010010011 +"
b0 *"
b100 )"
b0 '"
b11111111111100000000000010010011 &"
b11111111111100000000000010010011 $"
b100 #"
b0 ""
b100 !"
b11111111111111111111111111111110 ~
b11111111111111111111111111111111 }
bx |
b0 {
bx z
b11111111111111111111111111111111 y
b11111 x
b0 w
b1 v
b11111111111111111111111111111111 u
b11111111111100000000000010010011 t
b10 s
b1111111 r
b0 q
b11 p
b11111111111111111111111111111111 o
b0 n
b0 m
b10 l
b0 k
b1111111111111111 j
b1111111111111111 i
b0 h
b0 g
b0 f
b11111111111111111111111111111111 e
b10 d
b11111111111111111111111111111111 c
b11111111111111111111111111111111 b
b11111111111100000000000010010011 a
b11111111111111111111111111111111 `
b0 _
bx ^
b11111111111111111111111111111111 ]
b11111 \
b0 [
b1 Z
b1111111 Y
b0 X
b11 W
b11111111111111111111111111111111 V
b0 U
bx T
b11 S
0R
b10011 Q
b1111111 P
b0 O
bx N
bx M
bx L
bx K
bx J
bx I
xH
b11 F
1E
0D
0C
0B
0A
1@
0?
0>
0=
b11111111111111111111111111111111 <
b11111111111111111111111111111111 ;
x:
b0 9
b1111111 8
07
b11111111111111111111111111111111 6
b11111111111100000000000010010011 5
b0 4
b10011 3
b0 2
b100 1
b1 0
b0 /
bx .
b0 -
b11111 ,
x+
x*
b11111111111111111111111111111111 )
0(
b11111111111111111111111111111110 '
0&
0%
0$
1#
0"
bx !
$end
#5000
1H
0*
0+
1:
b0 .
b0 T
b0 ^
b0 z
b0 N
b0 M
b0 L
b0 K
b0 J
b0 !
b0 I
b100000 |
1"
#10000
0"
#15000
0#
b100000 |
1"
#20000
0"
#25000
b0 )
b0 ]
b0 y
b1111111111111111 k
b1111111111111111 m
b0 g
0H
1(
b0 <
b0 V
b0 c
b0 o
b0 j
b0 i
1+
0:
b11111111111111111111111111111111 /
b11111111111111111111111111111111 _
b11111111111111111111111111111111 n
b11111111111111111111111111111111 {
0E
1@
b10 F
b10 S
b10 W
b10 p
1=
b11111111111111111111111111111110 '
b11111111111111111111111111111110 ~
b0 `
b0 e
b1000 #"
b1000 )"
b0 ,
b0 \
b0 x
b1 -
b1 [
b1 w
b10 0
b10 Z
b10 v
b0 8
b0 P
b0 Y
b0 r
1R
b1011 3
b1011 Q
b0 6
b0 ,"
b0 b
b0 u
b1000000100001011 5
b1000000100001011 a
b1000000100001011 t
b1000000100001011 $"
b1000000100001011 &"
b1000000100001011 +"
b1 N
b1 J
b1 !
b1 I
b1000 !"
b100 ;
b100 }
b1000 1
b100 2
b100 ""
b100 '"
b100 *"
1"
#30000
0"
#35000
b101 )
b101 ]
b101 y
0(
b101 <
b101 V
b101 c
b101 o
b101 j
b0 k
b0 m
1H
b101 `
b101 e
0+
1:
b0 /
b0 _
b0 n
b0 {
1E
1@
b11 F
b11 S
b11 W
b11 p
0=
b100 '
b100 ~
b1100 #"
b1100 )"
b101 ,
b101 \
b101 x
b0 -
b0 [
b0 w
b11 0
b11 Z
b11 v
0R
b10011 3
b10011 Q
b101 b
b101 u
b101 6
b101 ,"
b10100000000000110010011 5
b10100000000000110010011 a
b10100000000000110010011 t
b10100000000000110010011 $"
b10100000000000110010011 &"
b10100000000000110010011 +"
b10 N
b1 M
b10 J
b10 !
b10 I
b1100 !"
b1101 ;
b1101 }
b1100 1
b1000 2
b1000 ""
b1000 '"
b1000 *"
1"
#40000
0"
#45000
b101 )
b101 ]
b101 y
b101 m
b101 g
0H
0(
b101 <
b101 V
b101 c
b101 o
b0 j
0:
b101 /
b101 _
b101 n
b101 {
0E
1@
b10 F
b10 S
b10 W
b10 p
1=
b100 '
b100 ~
b0 `
b0 e
b10000 #"
b10000 )"
b0 ,
b0 \
b0 x
b11 -
b11 [
b11 w
b100 0
b100 Z
b100 v
1R
b1011 3
b1011 Q
b0 6
b0 ,"
b0 b
b0 u
b11000001000001011 5
b11000001000001011 a
b11000001000001011 t
b11000001000001011 $"
b11000001000001011 &"
b11000001000001011 +"
b11 N
b11 J
b11 !
b11 I
b10000 !"
b1100 ;
b1100 }
b10000 1
b1100 2
b1100 ""
b1100 '"
b1100 *"
1"
#50000
0"
#55000
b10 )
b10 ]
b10 y
b10 j
b0 m
b0 g
1H
b10 `
b10 e
0(
b10 <
b10 V
b10 c
b10 o
1:
b0 /
b0 _
b0 n
b0 {
1E
1@
b11 F
b11 S
b11 W
b11 p
0=
b10 '
b10 ~
b10100 #"
b10100 )"
b10 ,
b10 \
b10 x
b0 -
b0 [
b0 w
b101 0
b101 Z
b101 v
0R
b10011 3
b10011 Q
b10 b
b10 u
b10 6
b10 ,"
b1000000000001010010011 5
b1000000000001010010011 a
b1000000000001010010011 t
b1000000000001010010011 $"
b1000000000001010010011 &"
b1000000000001010010011 +"
b100 N
b10 M
b100 J
b100 !
b100 I
b10100 !"
b10010 ;
b10010 }
b10100 1
b10000 2
b10000 ""
b10000 '"
b10000 *"
1"
#60000
0"
#65000
b11 )
b11 ]
b11 y
0H
b11 <
b11 V
b11 c
b11 o
b11 j
1*
1+
0:
b101 .
b101 T
b101 ^
b101 z
b11 `
b11 e
b11000 #"
b11000 )"
b11 ,
b11 \
b11 x
b110 0
b110 Z
b110 v
b11 6
b11 ,"
b11 b
b11 u
b1100000000001100010011 5
b1100000000001100010011 a
b1100000000001100010011 t
b1100000000001100010011 $"
b1100000000001100010011 &"
b1100000000001100010011 +"
b101 N
b101 J
b101 !
b101 I
b11000 !"
b10111 ;
b10111 }
b11000 1
b10100 2
b10100 ""
b10100 '"
b10100 *"
1"
#70000
0"
#75000
b110000000000000000 )
b110000000000000000 ]
b110000000000000000 y
b110000 f
b110000 h
b11 m
b11 g
b110000000000000000 <
b110000000000000000 V
b110000000000000000 c
b110000000000000000 o
b10000 j
0*
0+
b0 .
b0 T
b0 ^
b0 z
b11 /
b11 _
b11 n
b11 {
b100 d
b100 l
b100 s
1H
b10000 `
b10000 e
b10010 '
b10010 ~
b11100 #"
b11100 )"
b10000 ,
b10000 \
b10000 x
b110 -
b110 [
b110 w
b1 9
b1 O
b1 X
b1 q
b10000 b
b10000 u
b10000 6
b10000 ,"
b1000000110001001100010011 5
b1000000110001001100010011 a
b1000000110001001100010011 t
b1000000110001001100010011 $"
b1000000110001001100010011 &"
b1000000110001001100010011 +"
b110 N
b110 J
b110 !
b110 I
b11100 !"
b101000 ;
b101000 }
b11100 1
b11000 2
b11000 ""
b11000 '"
b11000 *"
1"
#80000
0"
#85000
b11 i
b110000000000000010 )
b110000000000000010 ]
b110000000000000010 y
b0 j
1*
1+
b110000000000000000 .
b110000000000000000 T
b110000000000000000 ^
b110000000000000000 z
b1 d
b1 l
b1 s
1H
0E
1@
b10 F
b10 S
b10 W
b10 p
b110000000000000000 `
b110000000000000000 e
b100000 #"
b100000 )"
b0 k
b0 f
b0 h
b10 m
b10 g
b10 '
b10 ~
0(
b110000000000000010 <
b110000000000000010 V
b110000000000000010 c
b110000000000000010 o
b110 ,
b110 \
b110 x
b101 -
b101 [
b101 w
b101 0
b101 Z
b101 v
b110 9
b110 O
b110 X
b110 q
b110011 3
b110011 Q
b0 6
b0 ,"
b0 b
b0 u
b10 /
b10 _
b10 n
b10 {
b11000101110001010110011 5
b11000101110001010110011 a
b11000101110001010110011 t
b11000101110001010110011 $"
b11000101110001010110011 &"
b11000101110001010110011 +"
b111 N
b11 M
b111 J
b111 !
b111 I
b100000 !"
b11100 ;
b11100 }
b100000 1
b11100 2
b11100 ""
b11100 '"
b11100 *"
1"
#90000
0"
