accel_cpu/src/alu.v
module alu (
    input wire [31:0] a, b,
    input wire [3:0] alu_control,
    input wire alu_ctrl_relu,
    input wire alu_ctrl_matmul,
    input wire alu_ctrl_dotprod,
    output reg [31:0] result,
    output wire zero
);

    assign zero = (result == 0);

    // ReLU
    wire [31:0] relu_out = (a[31] == 1'b1) ? 32'd0 : a;

    // Packed 16-bit operands
    wire [15:0] aa = a[15:0];
    wire [15:0] bb = a[31:16];
    wire [15:0] cc = b[15:0];
    wire [15:0] dd = b[31:16];
    wire [31:0] dot_out    = $signed(aa)*$signed(cc) + $signed(bb)*$signed(dd);
    wire [31:0] matmul_out = dot_out;

    always @(*) begin
        case (1'b1)
            alu_ctrl_relu:    result = relu_out;
            alu_ctrl_matmul:  result = matmul_out;
            alu_ctrl_dotprod: result = dot_out;
            default: begin
                case (alu_control)
                    4'b0000: result = a & b;                     // AND
                    4'b0001: result = a | b;                     // OR
                    4'b0010: result = a + b;                     // ADD
                    4'b0110: result = a - b;                     // SUB
                    4'b0011: result = a ^ b;                     // XOR
                    4'b0100: result = a << b[4:0];               // SLL
                    4'b0101: result = a >> b[4:0];               // SRL
                    4'b1101: result = $signed(a) >>> b[4:0];     // SRA
                    4'b0111: result = ($signed(a) < $signed(b)) ? 1 : 0; // SLT
                    4'b1000: result = (a < b) ? 1 : 0;           // SLTU
                    4'b1001: result = a * b;                     // MUL
                    default: result = 0;
                endcase
            end
        endcase
    end
endmodule

src/imm_gen.v
module imm_gen (
    input wire [31:0] instr,
    output reg [31:0] imm_out
);
    always @(*) begin
        case (instr[6:0])
            7'b0010011, // I-type ALU
            7'b0000011, // Loads
            7'b1100111: // JALR
                imm_out = {{20{instr[31]}}, instr[31:20]};
            7'b0100011: // S-type stores
                imm_out = {{20{instr[31]}}, instr[31:25], instr[11:7]};
            7'b1100011: // B-type branches
                imm_out = {{19{instr[31]}}, instr[31], instr[7], instr[30:25], instr[11:8], 1'b0};
            7'b0110111, // LUI
            7'b0010111: // AUIPC
                imm_out = {instr[31:12], 12'b0};
            7'b1101111: // J-type JAL
                imm_out = {{11{instr[31]}}, instr[31], instr[19:12], instr[20], instr[30:21], 1'b0};
            default:
                imm_out = 32'b0;
        endcase
    end
endmodule

accel_cpu/src/alu_control.v
module alu_control (
    input wire [1:0] ALUOp,
    input wire [2:0] funct3,
    input wire [6:0] funct7,
    output reg [3:0] alu_control
);
    always @(*) begin
        case (ALUOp)
            2'b00: alu_control = 4'b0010;  // lw, sw → ADD
            2'b01: alu_control = 4'b0110;  // branch → SUB
            2'b10: begin  // R-type
                case ({funct7, funct3})
                    10'b0000000_000: alu_control = 4'b0010; // ADD
                    10'b0100000_000: alu_control = 4'b0110; // SUB
                    10'b0000000_001: alu_control = 4'b0100; // SLL
                    10'b0000000_010: alu_control = 4'b0111; // SLT
                    10'b0000000_011: alu_control = 4'b1000; // SLTU
                    10'b0000000_100: alu_control = 4'b0011; // XOR
                    10'b0000000_101: alu_control = 4'b0101; // SRL
                    10'b0100000_101: alu_control = 4'b1101; // SRA
                    10'b0000000_110: alu_control = 4'b0001; // OR
                    10'b0000000_111: alu_control = 4'b0000; // AND
                    10'b0000001_000: alu_control = 4'b1001; // MUL
                    default: alu_control = 4'b1111; // INVALID
                endcase
            end
            2'b11: begin  // I-type ALU ops
                case (funct3)
                    3'b000: alu_control = 4'b0010; // ADDI
                    3'b010: alu_control = 4'b0111; // SLTI
                    3'b011: alu_control = 4'b1000; // SLTIU
                    3'b100: alu_control = 4'b0011; // XORI
                    3'b110: alu_control = 4'b0001; // ORI
                    3'b111: alu_control = 4'b0000; // ANDI
                    3'b001: alu_control = 4'b0100; // SLLI
                    3'b101: alu_control = (funct7[5]) ? 4'b1101 : 4'b0101; // SRAI / SRLI
                    default: alu_control = 4'b1111;
                endcase
            end
            default: alu_control = 4'b1111;
        endcase
    end
endmodule

src/regfile.v
module regfile (
    input wire clk,
    input wire reset,
    input wire we,                         // Write enable
    input wire [4:0] rs1, rs2, rd,         // Register addresses
    input wire [31:0] wd,                  // Write data
    output wire [31:0] rd1, rd2            // Read data outputs
);
    reg [31:0] regs [0:31];

    // Read (asynchronous)
    assign rd1 = (rs1 == 0) ? 0 : regs[rs1];
    assign rd2 = (rs2 == 0) ? 0 : regs[rs2];

    // Write with synchronous reset
    integer i;
    always @(posedge clk) begin
        if (reset) begin
            for (i = 0; i < 32; i = i + 1)
                regs[i] <= 0;
        end else if (we && (rd != 0)) begin
            regs[rd] <= wd;
        end
    end
endmodule

accel_cpu/src/execute.v
module execute (
    input wire clk,
    input wire reset,
    input wire we,                     // Write enable for register file
    input wire [1:0] alu_op,          // ALUOp from control unit
    input wire [4:0] rs1, rs2, rd,    // Register addresses
    input wire [31:0] instr,          // Full instruction for immediate generation
    input wire alu_src,               // Select between register or immediate
    input wire [2:0] funct3,
    input wire [6:0] funct7,
    input wire alu_ctrl_relu,
    input wire alu_ctrl_matmul,
    input wire alu_ctrl_dotprod,
    input wire [31:0] wb_data,        // Data to write back to register file
    output wire [31:0] alu_result,
    output wire zero,
    output wire [31:0] rd1, rd2
);

    wire [31:0] op2;
    wire [3:0] alu_control;
    wire [31:0] imm;

    // Register file
    regfile rf (
        .clk(clk),
        .reset(reset),
        .we(we),
        .rs1(rs1),
        .rs2(rs2),
        .rd(rd),
        .wd(wb_data),
        .rd1(rd1),
        .rd2(rd2)
    );

    // ALU control
    alu_control alu_ctl (
        .ALUOp(alu_op),
        .funct3(funct3),
        .funct7(funct7),
        .alu_control(alu_control)
    );

    // Immediate generator
    imm_gen imm_generator (
        .instr(instr),
        .imm_out(imm)
    );

    // ALU second operand selection
    assign op2 = (alu_src) ? imm : rd2;

    // ALU
    alu alu_core (
        .a(rd1),
        .b(op2),
        .alu_control(alu_control),
        .alu_ctrl_relu(alu_ctrl_relu),
        .alu_ctrl_matmul(alu_ctrl_matmul),
        .alu_ctrl_dotprod(alu_ctrl_dotprod),
        .result(alu_result),
        .zero(zero)
    );

endmodule

base_cpu/src/data_mem.v
module data_mem(
    input wire clk,
    input wire mem_read,
    input wire mem_write,
    input wire [31:0] addr,
    input wire [31:0] write_data,
    output wire [31:0] read_data
);
    reg [31:0] mem [0:255];

    initial begin
        // Optionally pre-load memory from file
    end

    always @(posedge clk) begin
        if (mem_write) begin
            mem[addr[9:2]] <= write_data;
        end
    end

    assign read_data = mem_read ? mem[addr[9:2]] : 32'b0;
endmodule

accel_cpu/src/control_unit.v
module control_unit(
    input  wire [6:0] opcode,
    input  wire [2:0] funct3,
    input  wire [6:0] funct7,
    output reg  [1:0] ALUOp,
    output reg  RegWrite,
    output reg  MemRead,
    output reg  MemWrite,
    output reg  Branch,
    output reg  Jump,
    output reg  ALUSrc,
    output wire alu_ctrl_relu,
    output wire alu_ctrl_matmul,
    output wire alu_ctrl_dotprod
);

    // Custom instruction detection
    wire is_custom0 = (opcode == 7'b0001011);
    assign alu_ctrl_relu    = is_custom0 && (funct3 == 3'b000);
    assign alu_ctrl_matmul  = is_custom0 && (funct3 == 3'b001);
    assign alu_ctrl_dotprod = is_custom0 && (funct3 == 3'b010);

    always @(*) begin
        // Default values
        ALUOp    = 2'b00;
        RegWrite = 0;
        MemRead  = 0;
        MemWrite = 0;
        Branch   = 0;
        Jump     = 0;
        ALUSrc   = 0;

        case (opcode)
            7'b0110011: begin // R-type
                RegWrite = 1;
                ALUOp    = 2'b10;
                ALUSrc   = 0;
            end
            7'b0010011: begin // I-type ALU
                RegWrite = 1;
                ALUOp    = 2'b11;
                ALUSrc   = 1;
            end
            7'b0000011: begin // Load
                RegWrite = 1;
                MemRead  = 1;
                ALUOp    = 2'b00;
                ALUSrc   = 1;
            end
            7'b0100011: begin // Store
                MemWrite = 1;
                ALUOp    = 2'b00;
                ALUSrc   = 1;
            end
            7'b1100011: begin // Branch
                Branch   = 1;
                ALUOp    = 2'b01;
                ALUSrc   = 0;
            end
            7'b1101111: begin // JAL
                Jump     = 1;
                RegWrite = 1;
            end
            7'b1100111: begin // JALR
                Jump     = 1;
                RegWrite = 1;
                ALUSrc   = 1;
                ALUOp    = 2'b00;
            end
            7'b0001011: begin // custom-0
                RegWrite = 1;
                ALUOp    = 2'b10;
            end
            default: begin
            end
        endcase
    end
endmodule

src/instr_mem.v
module instr_mem #(
    parameter INIT_FILE = "program.mem"
) (
    input wire [31:0] addr,
    output wire [31:0] instr
);
    reg [31:0] mem [0:255];  // 1KB instruction memory (256 words)

    initial begin
        $readmemh(INIT_FILE, mem);  // Load instructions from hex file
    end

    assign instr = mem[addr[9:2]];  // Word-aligned address (ignore bottom 2 bits)
endmodule

accel_cpu/src/pc.v
module pc(
    input wire clk,
    input wire reset,
    input wire [31:0] next_pc,
    output reg [31:0] pc_out
);
    always @(posedge clk or posedge reset) begin
        if (reset)
            pc_out <= 32'h00000000;
        else
            pc_out <= next_pc;
    end
endmodule

src/cpu_fetch.v
module cpu_fetch #(
    parameter MEMFILE = "program.mem"
) (
    input  wire        clk,
    input  wire        reset,

    // Control signals / targets
    input  wire        jal,            // jal instruction
    input  wire        jalr,           // jalr instruction
    input  wire        branch,         // conditional branch instruction
    input  wire        branch_taken,   // result of branch comparison from ALU
    input  wire [31:0] branch_target,  // PC-relative target for jal/branch
    input  wire [31:0] jalr_target,    // Target address for jalr

    output wire [31:0] instr,
    output wire [31:0] pc_out
);
    wire [31:0] next_pc;

    // Program Counter instance
    pc pc_inst (
        .clk(clk),
        .reset(reset),
        .next_pc(next_pc),
        .pc_out(pc_out)
    );

    // Instruction Memory instance
    instr_mem #(.INIT_FILE(MEMFILE)) imem (
        .addr(pc_out),
        .instr(instr)
    );

    // Next PC generation with branch/jump handling
    wire [31:0] pc_plus4 = pc_out + 4;

    assign next_pc = jal  ? branch_target :
                     jalr ? jalr_target  :
                     (branch && branch_taken) ? branch_target :
                     pc_plus4;

endmodule

accel_cpu/src/cpu.v
module cpu #(
    parameter MEMFILE = "program.mem"
) (
    input wire clk,
    input wire reset,
    output reg [31:0] cycle_count
);
    wire [31:0] instr;
    wire [31:0] pc_out;

    // Performance counters
    reg [31:0] instr_count;
    reg [31:0] mem_read_count;
    reg [31:0] mem_write_count;
    reg [31:0] rf_read_count;
    reg [31:0] rf_write_count;

    // Signals for fetch stage
    wire jal, jalr;
    wire branch_taken;
    wire [31:0] branch_target, jalr_target;

    cpu_fetch #(.MEMFILE(MEMFILE)) fetch_unit(
        .clk(clk),
        .reset(reset),
        .jal(jal),
        .jalr(jalr),
        .branch(Branch),
        .branch_taken(branch_taken),
        .branch_target(branch_target),
        .jalr_target(jalr_target),
        .instr(instr),
        .pc_out(pc_out)
    );

    // Decode fields
    wire [6:0] opcode = instr[6:0];
    wire [2:0] funct3 = instr[14:12];
    wire [6:0] funct7 = instr[31:25];

    // Halt detection (using the EBREAK instruction)
    wire halt = (instr == 32'h0010_0073);
    wire [4:0] rd  = instr[11:7];
    wire [4:0] rs1 = instr[19:15];
    wire [4:0] rs2 = instr[24:20];

    // Immediate generator
    wire [31:0] imm;
    imm_gen imm_unit(
        .instr(instr),
        .imm_out(imm)
    );

    // Control signals
    wire [1:0] ALUOp;
    wire RegWrite, MemRead, MemWrite, Branch, Jump, ALUSrc;
    wire alu_ctrl_relu, alu_ctrl_matmul, alu_ctrl_dotprod;

    control_unit cu(
        .opcode(opcode),
        .funct3(funct3),
        .funct7(funct7),
        .ALUOp(ALUOp),
        .RegWrite(RegWrite),
        .MemRead(MemRead),
        .MemWrite(MemWrite),
        .Branch(Branch),
        .Jump(Jump),
        .ALUSrc(ALUSrc),
        .alu_ctrl_relu(alu_ctrl_relu),
        .alu_ctrl_matmul(alu_ctrl_matmul),
        .alu_ctrl_dotprod(alu_ctrl_dotprod)
    );

    // Register and ALU outputs
    wire [31:0] alu_result;
    wire zero;
    wire [31:0] rd1, rd2;
    wire [31:0] write_back_data;

    // Data memory
    wire [31:0] mem_data;
    data_mem dmem(
        .clk(clk),
        .mem_read(MemRead),
        .mem_write(MemWrite),
        .addr(alu_result),
        .write_data(rd2),
        .read_data(mem_data)
    );


    execute exec_unit(
        .clk(clk),
        .reset(reset),
        .we(RegWrite),
        .alu_op(ALUOp),
        .rs1(rs1),
        .rs2(rs2),
        .rd(rd),
        .instr(instr),
        .alu_src(ALUSrc),
        .funct3(funct3),
        .funct7(funct7),
        .alu_ctrl_relu(alu_ctrl_relu),
        .alu_ctrl_matmul(alu_ctrl_matmul),
        .alu_ctrl_dotprod(alu_ctrl_dotprod),
        .wb_data(write_back_data),
        .alu_result(alu_result),
        .zero(zero),
        .rd1(rd1),
        .rd2(rd2)
    );

    // PC increment
    wire [31:0] pc_plus4 = pc_out + 4;

    // Branch and jump target calculations
    assign branch_target = pc_out + imm;
    assign jalr_target   = (rd1 + imm) & 32'hffff_fffe;

    // Branch comparison helpers
    wire eq      = (rd1 == rd2);
    wire slt     = ($signed(rd1) < $signed(rd2));
    wire sltu    = (rd1 < rd2);

    // Branch decision based on funct3
    reg branch_cond;
    always @(*) begin
        case (funct3)
            3'b000: branch_cond = eq;          // BEQ
            3'b001: branch_cond = !eq;         // BNE
            3'b100: branch_cond = slt;         // BLT
            3'b101: branch_cond = !slt;        // BGE
            3'b110: branch_cond = sltu;        // BLTU
            3'b111: branch_cond = !sltu;       // BGEU
            default: branch_cond = 1'b0;
        endcase
    end

    assign branch_taken = Branch && branch_cond;

    // Distinguish between JAL and JALR
    assign jal  = Jump && (opcode == 7'b1101111);
    assign jalr = Jump && (opcode == 7'b1100111);

    // Writeback mux: priority Jump -> Load -> ALU
    assign write_back_data = jal | jalr ? pc_plus4 :
                              MemRead    ? mem_data  :
                              alu_result;

    // Cycle counter and other performance metrics
    always @(posedge clk) begin
        if (reset) begin
            cycle_count     <= 0;
            instr_count     <= 0;
            mem_read_count  <= 0;
            mem_write_count <= 0;
            rf_read_count   <= 0;
            rf_write_count  <= 0;
        end else if (!halt) begin
            cycle_count <= cycle_count + 1;
            instr_count <= instr_count + 1;

            // Memory access counters
            if (MemRead)
                mem_read_count <= mem_read_count + 1;
            if (MemWrite)
                mem_write_count <= mem_write_count + 1;

            // Register file read counters
            if ((opcode != 7'b1101111) && (rs1 != 0))
                rf_read_count <= rf_read_count + 1;
            if ((opcode == 7'b0110011 || opcode == 7'b0100011 || opcode == 7'b1100011) && (rs2 != 0))
                rf_read_count <= rf_read_count + 1;

            // Register file write counter
            if (RegWrite && rd != 0)
                rf_write_count <= rf_write_count + 1;
        end
    end

    // TODO: Power estimation hooks can be added for FPGA implementation
endmodule

accel_cpu/testbench/cpu_relu_tb.v
`timescale 1ns / 1ps

module cpu_relu_tb;
    reg clk = 0;
    reg reset;
    wire [31:0] cycle_count;
    wire [31:0] instr_count      = uut.instr_count;
    wire [31:0] mem_read_count   = uut.mem_read_count;
    wire [31:0] mem_write_count  = uut.mem_write_count;
    wire [31:0] rf_read_count    = uut.rf_read_count;
    wire [31:0] rf_write_count   = uut.rf_write_count;

    cpu #(.MEMFILE("test_mem/relu.mem")) uut (
        .clk(clk),
        .reset(reset),
        .cycle_count(cycle_count)
    );

    always #5 clk = ~clk;

    initial begin
        $dumpfile("sim/cpu_relu_tb.vcd");
        $dumpvars(0, cpu_relu_tb);
        $display("=== ReLU Benchmark ===");

        reset = 1;
        @(posedge clk); @(posedge clk); reset = 0;

        repeat(25) @(posedge clk); #1;
        $display("Result memory: %0d %0d %0d %0d",
                 uut.dmem.mem[0], uut.dmem.mem[1],
                 uut.dmem.mem[2], uut.dmem.mem[3]);
        $display("Cycles       : %0d", cycle_count);
        $display("Instructions : %0d", instr_count);
        $display("Mem reads    : %0d", mem_read_count);
        $display("Mem writes   : %0d", mem_write_count);
        $display("RF reads     : %0d", rf_read_count);
        $display("RF writes    : %0d", rf_write_count);
        $finish;
    end
endmodule

accel_cpu/sim/cpu_relu_tb.vcd
$date
	Tue Jul  1 01:54:22 2025
$end
$version
	Icarus Verilog
$end
$timescale
	1ps
$end
$scope module cpu_relu_tb $end
$var wire 32 ! instr_count [31:0] $end
$var wire 32 " mem_read_count [31:0] $end
$var wire 32 # mem_write_count [31:0] $end
$var wire 32 $ rf_read_count [31:0] $end
$var wire 32 % rf_write_count [31:0] $end
$var wire 32 & cycle_count [31:0] $end
$var reg 1 ' clk $end
$var reg 1 ( reset $end
$scope module uut $end
$var wire 1 ) branch_taken $end
$var wire 1 ' clk $end
$var wire 1 * jal $end
$var wire 1 + jalr $end
$var wire 32 , jalr_target [31:0] $end
$var wire 1 ( reset $end
$var wire 1 - zero $end
$var wire 32 . write_back_data [31:0] $end
$var wire 1 / sltu $end
$var wire 1 0 slt $end
$var wire 5 1 rs2 [4:0] $end
$var wire 5 2 rs1 [4:0] $end
$var wire 32 3 rd2 [31:0] $end
$var wire 32 4 rd1 [31:0] $end
$var wire 5 5 rd [4:0] $end
$var wire 32 6 pc_plus4 [31:0] $end
$var wire 32 7 pc_out [31:0] $end
$var wire 7 8 opcode [6:0] $end
$var wire 32 9 mem_data [31:0] $end
$var wire 32 : instr [31:0] $end
$var wire 32 ; imm [31:0] $end
$var wire 1 < halt $end
$var wire 7 = funct7 [6:0] $end
$var wire 3 > funct3 [2:0] $end
$var wire 1 ? eq $end
$var wire 32 @ branch_target [31:0] $end
$var wire 32 A alu_result [31:0] $end
$var wire 1 B alu_ctrl_relu $end
$var wire 1 C alu_ctrl_matmul $end
$var wire 1 D alu_ctrl_dotprod $end
$var wire 1 E RegWrite $end
$var wire 1 F MemWrite $end
$var wire 1 G MemRead $end
$var wire 1 H Jump $end
$var wire 1 I Branch $end
$var wire 1 J ALUSrc $end
$var wire 2 K ALUOp [1:0] $end
$var parameter 136 L MEMFILE $end
$var reg 1 M branch_cond $end
$var reg 32 N cycle_count [31:0] $end
$var reg 32 O instr_count [31:0] $end
$var reg 32 P mem_read_count [31:0] $end
$var reg 32 Q mem_write_count [31:0] $end
$var reg 32 R rf_read_count [31:0] $end
$var reg 32 S rf_write_count [31:0] $end
$scope module cu $end
$var wire 1 D alu_ctrl_dotprod $end
$var wire 1 C alu_ctrl_matmul $end
$var wire 1 B alu_ctrl_relu $end
$var wire 3 T funct3 [2:0] $end
$var wire 7 U funct7 [6:0] $end
$var wire 7 V opcode [6:0] $end
$var wire 1 W is_custom0 $end
$var reg 2 X ALUOp [1:0] $end
$var reg 1 J ALUSrc $end
$var reg 1 I Branch $end
$var reg 1 H Jump $end
$var reg 1 G MemRead $end
$var reg 1 F MemWrite $end
$var reg 1 E RegWrite $end
$upscope $end
$scope module dmem $end
$var wire 1 ' clk $end
$var wire 1 G mem_read $end
$var wire 1 F mem_write $end
$var wire 32 Y write_data [31:0] $end
$var wire 32 Z read_data [31:0] $end
$var wire 32 [ addr [31:0] $end
$upscope $end
$scope module exec_unit $end
$var wire 1 D alu_ctrl_dotprod $end
$var wire 1 C alu_ctrl_matmul $end
$var wire 1 B alu_ctrl_relu $end
$var wire 2 \ alu_op [1:0] $end
$var wire 1 J alu_src $end
$var wire 1 ' clk $end
$var wire 3 ] funct3 [2:0] $end
$var wire 7 ^ funct7 [6:0] $end
$var wire 5 _ rd [4:0] $end
$var wire 1 ( reset $end
$var wire 5 ` rs1 [4:0] $end
$var wire 5 a rs2 [4:0] $end
$var wire 32 b wb_data [31:0] $end
$var wire 1 E we $end
$var wire 1 - zero $end
$var wire 32 c rd2 [31:0] $end
$var wire 32 d rd1 [31:0] $end
$var wire 32 e op2 [31:0] $end
$var wire 32 f instr [31:0] $end
$var wire 32 g imm [31:0] $end
$var wire 32 h alu_result [31:0] $end
$var wire 4 i alu_control [3:0] $end
$scope module alu_core $end
$var wire 1 D alu_ctrl_dotprod $end
$var wire 1 C alu_ctrl_matmul $end
$var wire 1 B alu_ctrl_relu $end
$var wire 32 j b [31:0] $end
$var wire 32 k matmul_out [31:0] $end
$var wire 1 - zero $end
$var wire 32 l relu_out [31:0] $end
$var wire 32 m dot_out [31:0] $end
$var wire 16 n dd [15:0] $end
$var wire 16 o cc [15:0] $end
$var wire 16 p bb [15:0] $end
$var wire 4 q alu_control [3:0] $end
$var wire 16 r aa [15:0] $end
$var wire 32 s a [31:0] $end
$var reg 32 t result [31:0] $end
$upscope $end
$scope module alu_ctl $end
$var wire 2 u ALUOp [1:0] $end
$var wire 3 v funct3 [2:0] $end
$var wire 7 w funct7 [6:0] $end
$var reg 4 x alu_control [3:0] $end
$upscope $end
$scope module imm_generator $end
$var wire 32 y instr [31:0] $end
$var reg 32 z imm_out [31:0] $end
$upscope $end
$scope module rf $end
$var wire 1 ' clk $end
$var wire 5 { rd [4:0] $end
$var wire 1 ( reset $end
$var wire 5 | rs1 [4:0] $end
$var wire 5 } rs2 [4:0] $end
$var wire 32 ~ wd [31:0] $end
$var wire 1 E we $end
$var wire 32 !" rd2 [31:0] $end
$var wire 32 "" rd1 [31:0] $end
$var integer 32 #" i [31:0] $end
$upscope $end
$upscope $end
$scope module fetch_unit $end
$var wire 1 I branch $end
$var wire 1 ) branch_taken $end
$var wire 32 $" branch_target [31:0] $end
$var wire 1 ' clk $end
$var wire 1 * jal $end
$var wire 1 + jalr $end
$var wire 32 %" jalr_target [31:0] $end
$var wire 1 ( reset $end
$var wire 32 &" pc_plus4 [31:0] $end
$var wire 32 '" pc_out [31:0] $end
$var wire 32 (" next_pc [31:0] $end
$var wire 32 )" instr [31:0] $end
$var parameter 136 *" MEMFILE $end
$scope module imem $end
$var wire 32 +" instr [31:0] $end
$var wire 32 ," addr [31:0] $end
$var parameter 136 -" INIT_FILE $end
$upscope $end
$scope module pc_inst $end
$var wire 1 ' clk $end
$var wire 32 ." next_pc [31:0] $end
$var wire 1 ( reset $end
$var reg 32 /" pc_out [31:0] $end
$upscope $end
$upscope $end
$scope module imm_unit $end
$var wire 32 0" instr [31:0] $end
$var reg 32 1" imm_out [31:0] $end
$upscope $end
$upscope $end
$upscope $end
$enddefinitions $end
$comment Show the parameter values. $end
$dumpall
b111010001100101011100110111010001011111011011010110010101101101001011110111001001100101011011000111010100101110011011010110010101101101 -"
b111010001100101011100110111010001011111011011010110010101101101001011110111001001100101011011000111010100101110011011010110010101101101 *"
b111010001100101011100110111010001011111011011010110010101101101001011110111001001100101011011000111010100101110011011010110010101101101 L
$end
#0
$dumpvars
b0 1"
b10010011 0"
b0 /"
b100 ."
b0 ,"
b10010011 +"
b10010011 )"
b100 ("
b0 '"
b100 &"
b0 %"
b0 $"
bx #"
b0 ""
b0 !"
b0 ~
b0 }
b0 |
b1 {
b0 z
b10010011 y
b10 x
b0 w
b0 v
b11 u
b0 t
b0 s
b0 r
b10 q
b0 p
b0 o
b0 n
b0 m
b0 l
b0 k
b0 j
b10 i
b0 h
b0 g
b10010011 f
b0 e
b0 d
b0 c
b0 b
b0 a
b0 `
b1 _
b0 ^
b0 ]
b11 \
b0 [
b0 Z
b0 Y
b11 X
0W
b10011 V
b0 U
b0 T
bx S
bx R
bx Q
bx P
bx O
bx N
1M
b11 K
1J
0I
0H
0G
0F
1E
0D
0C
0B
b0 A
b0 @
1?
b0 >
b0 =
0<
b0 ;
b10010011 :
b0 9
b10011 8
b0 7
b100 6
b1 5
b0 4
b0 3
b0 2
b0 1
00
0/
b0 .
1-
b0 ,
0+
0*
0)
1(
0'
bx &
bx %
bx $
bx #
bx "
bx !
$end
#5000
b0 %
b0 S
b0 $
b0 R
b0 #
b0 Q
b0 "
b0 P
b0 !
b0 O
b0 &
b0 N
b100000 #"
1'
#10000
0'
#15000
0(
b100000 #"
1'
#20000
0'
#25000
b11111111111111111111111111111110 .
b11111111111111111111111111111110 b
b11111111111111111111111111111110 ~
0-
b11111111111111111111111111111110 A
b11111111111111111111111111111110 [
b11111111111111111111111111111110 h
b11111111111111111111111111111110 t
b1111111111111110 o
b1111111111111111 n
b11111111111111111111111111111110 ,
b11111111111111111111111111111110 %"
b11111111111111111111111111111110 e
b11111111111111111111111111111110 j
b1000 ("
b1000 ."
b11110 1
b11110 a
b11110 }
b10 5
b10 _
b10 {
b1111111 =
b1111111 U
b1111111 ^
b1111111 w
b11111111111111111111111111111110 ;
b11111111111111111111111111111110 1"
b11111111111111111111111111111110 g
b11111111111111111111111111111110 z
b11111111111000000000000100010011 :
b11111111111000000000000100010011 f
b11111111111000000000000100010011 y
b11111111111000000000000100010011 )"
b11111111111000000000000100010011 +"
b11111111111000000000000100010011 0"
b1 %
b1 S
b1 !
b1 O
b1 &
b1 N
b1000 &"
b10 @
b10 $"
b1000 6
b100 7
b100 '"
b100 ,"
b100 /"
1'
#30000
0'
#35000
b0 .
b0 b
b0 ~
1-
b0 A
b0 [
b0 h
b0 t
b0 o
b0 n
1/
0?
b11111111111111111111111111111110 3
b11111111111111111111111111111110 Y
b11111111111111111111111111111110 c
b11111111111111111111111111111110 !"
0M
1F
1J
0E
b0 K
b0 X
b0 \
b0 u
b0 e
b0 j
b0 ,
b0 %"
b1100 ("
b1100 ."
b10 1
b10 a
b10 }
b1 2
b1 `
b1 |
b0 5
b0 _
b0 {
b0 =
b0 U
b0 ^
b0 w
b10 >
b10 T
b10 ]
b10 v
b100011 8
b100011 V
b0 g
b0 z
b0 ;
b0 1"
b1000001010000000100011 :
b1000001010000000100011 f
b1000001010000000100011 y
b1000001010000000100011 )"
b1000001010000000100011 +"
b1000001010000000100011 0"
b10 %
b10 S
b10 !
b10 O
b10 &
b10 N
b1100 &"
b1000 @
b1000 $"
b1100 6
b1000 7
b1000 '"
b1000 ,"
b1000 /"
1'
#40000
0'
#45000
b111 .
b111 b
b111 ~
1M
0-
b111 A
b111 [
b111 h
b111 t
b111 o
0/
1?
b0 3
b0 Y
b0 c
b0 !"
b11 K
b11 X
b11 \
b11 u
1E
1J
0F
b110 ,
b110 %"
b111 e
b111 j
b10000 ("
b10000 ."
b111 1
b111 a
b111 }
b0 2
b0 `
b0 |
b10 5
b10 _
b10 {
b0 >
b0 T
b0 ]
b0 v
b10011 8
b10011 V
b111 ;
b111 1"
b111 g
b111 z
b11100000000000100010011 :
b11100000000000100010011 f
b11100000000000100010011 y
b11100000000000100010011 )"
b11100000000000100010011 +"
b11100000000000100010011 0"
b1 $
b1 R
b1 #
b1 Q
b11 !
b11 O
b11 &
b11 N
b10000 &"
b10011 @
b10011 $"
b10000 6
b1100 7
b1100 '"
b1100 ,"
b1100 /"
1'
#50000
0'
#55000
b100 .
b100 b
b100 ~
b100 A
b100 [
b100 h
b100 t
b100 o
1/
10
0?
b111 3
b111 Y
b111 c
b111 !"
0M
1F
1J
0E
b0 K
b0 X
b0 \
b0 u
b100 e
b100 j
b100 ,
b100 %"
b10100 ("
b10100 ."
b10 1
b10 a
b10 }
b1 2
b1 `
b1 |
b100 5
b100 _
b100 {
b10 >
b10 T
b10 ]
b10 v
b100011 8
b100011 V
b100 g
b100 z
b100 ;
b100 1"
b1000001010001000100011 :
b1000001010001000100011 f
b1000001010001000100011 y
b1000001010001000100011 )"
b1000001010001000100011 +"
b1000001010001000100011 0"
b11 %
b11 S
b100 !
b100 O
b100 &
b100 N
b10100 &"
b10100 @
b10100 $"
b10100 6
b10000 7
b10000 '"
b10000 ,"
b10000 /"
1'
#60000
0'
#65000
b11111111111111111111111111111111 .
b11111111111111111111111111111111 b
b11111111111111111111111111111111 ~
1M
b11111111111111111111111111111111 A
b11111111111111111111111111111111 [
b11111111111111111111111111111111 h
b11111111111111111111111111111111 t
b1111111111111111 o
b1111111111111111 n
0/
00
1?
b0 3
b0 Y
b0 c
b0 !"
b11 K
b11 X
b11 \
b11 u
1E
1J
0F
b11111111111111111111111111111110 ,
b11111111111111111111111111111110 %"
b11111111111111111111111111111111 e
b11111111111111111111111111111111 j
b11000 ("
b11000 ."
b11111 1
b11111 a
b11111 }
b0 2
b0 `
b0 |
b10 5
b10 _
b10 {
b1111111 =
b1111111 U
b1111111 ^
b1111111 w
b0 >
b0 T
b0 ]
b0 v
b10011 8
b10011 V
b11111111111111111111111111111111 ;
b11111111111111111111111111111111 1"
b11111111111111111111111111111111 g
b11111111111111111111111111111111 z
b11111111111100000000000100010011 :
b11111111111100000000000100010011 f
b11111111111100000000000100010011 y
b11111111111100000000000100010011 )"
b11111111111100000000000100010011 +"
b11111111111100000000000100010011 0"
b10 $
b10 R
b10 #
b10 Q
b101 !
b101 O
b101 &
b101 N
b11000 &"
b10011 @
b10011 $"
b11000 6
b10100 7
b10100 '"
b10100 ,"
b10100 /"
1'
#70000
0'
#75000
b1000 .
b1000 b
b1000 ~
b1000 A
b1000 [
b1000 h
b1000 t
b1000 o
b0 n
1/
0?
b11111111111111111111111111111111 3
b11111111111111111111111111111111 Y
b11111111111111111111111111111111 c
b11111111111111111111111111111111 !"
0M
1F
1J
0E
b0 K
b0 X
b0 \
b0 u
b1000 e
b1000 j
b1000 ,
b1000 %"
b11100 ("
b11100 ."
b10 1
b10 a
b10 }
b1 2
b1 `
b1 |
b1000 5
b1000 _
b1000 {
b0 =
b0 U
b0 ^
b0 w
b10 >
b10 T
b10 ]
b10 v
b100011 8
b100011 V
b1000 g
b1000 z
b1000 ;
b1000 1"
b1000001010010000100011 :
b1000001010010000100011 f
b1000001010010000100011 y
b1000001010010000100011 )"
b1000001010010000100011 +"
b1000001010010000100011 0"
b100 %
b100 S
b110 !
b110 O
b110 &
b110 N
b11100 &"
b100000 @
b100000 $"
b11100 6
b11000 7
b11000 '"
b11000 ,"
b11000 /"
1'
#80000
0'
